<?xml version="1.0" encoding="utf-8"?>
<root>
  <act name="SkillA" totalFrame="88">
    <drop_shadow>
      <data pos="0.1|-370.7" frame="1" m="1.418|0.000|0.000|1.251"/>
      <data pos="0.15|-370.7" frame="2" m="1.418|0.000|0.000|1.251"/>
      <data pos="0.15|-370.7" frame="3" m="1.418|0.000|0.000|1.251"/>
      <data pos="0.15|-370.7" frame="4" m="1.418|0.000|0.000|1.251"/>
      <data pos="0.15|-370.7" frame="5" m="1.418|0.000|0.000|1.251"/>
      <data pos="0.15|-370.7" frame="6" m="1.418|0.000|0.000|1.251"/>
      <data pos="0.15|-370.7" frame="7" m="1.418|0.000|0.000|1.251"/>
      <data pos="0.1|-370.7" frame="8" m="1.418|0.000|0.000|1.251"/>
      <data pos="0.1|-370.7" frame="9" m="1.418|0.000|0.000|1.251"/>
      <data pos="0.1|-370.7" frame="10" m="1.418|0.000|0.000|1.251"/>
      <data pos="0.15|-370.7" frame="11" m="1.418|0.000|0.000|1.251"/>
      <data pos="0.1|-370.7" frame="12" m="1.418|0.000|0.000|1.251"/>
      <data pos="0.15|-370.7" frame="13" m="1.418|0.000|0.000|1.251"/>
      <data pos="0.15|-370.7" frame="14" m="1.418|0.000|0.000|1.251"/>
      <data pos="0.15|-370.7" frame="15" m="1.418|0.000|0.000|1.251"/>
      <data pos="0.15|-370.7" frame="16" m="1.418|0.000|0.000|1.251"/>
      <data pos="0.15|-370.7" frame="17" m="1.418|0.000|0.000|1.251"/>
      <data pos="0.15|-370.7" frame="18" m="1.418|0.000|0.000|1.251"/>
      <data pos="0.15|-370.7" frame="19" m="1.418|0.000|0.000|1.251"/>
      <data pos="0.15|-370.7" frame="20" m="1.418|0.000|0.000|1.251"/>
      <data pos="0.15|-370.7" frame="21" m="1.418|0.000|0.000|1.251"/>
      <data pos="0.15|-370.7" frame="22" m="1.418|0.000|0.000|1.251"/>
      <data pos="0.15|-370.7" frame="23" m="1.418|0.000|0.000|1.251"/>
      <data pos="0.15|-370.7" frame="24" m="1.418|0.000|0.000|1.251"/>
      <data pos="0.15|-370.7" frame="25" m="1.418|0.000|0.000|1.251"/>
      <data pos="0.15|-370.7" frame="26" m="1.418|0.000|0.000|1.251"/>
      <data pos="0.15|-370.7" frame="27" m="1.418|0.000|0.000|1.251"/>
      <data pos="0.1|-370.7" frame="28" m="1.418|0.000|0.000|1.251"/>
      <data pos="0.1|-370.7" frame="29" m="1.418|0.000|0.000|1.251"/>
      <data pos="-19.05|-370.7" frame="30" m="1.418|0.000|0.000|1.251"/>
      <data pos="-38.25|-370.7" frame="31" m="1.418|0.000|0.000|1.251"/>
      <data pos="-57.45|-370.7" frame="32" m="1.418|0.000|0.000|1.251"/>
      <data pos="-76.65|-370.7" frame="33" m="1.418|0.000|0.000|1.251"/>
      <data pos="-95.9|-370.7" frame="34" m="1.418|0.000|0.000|1.251"/>
      <data pos="-95.9|-370.7" frame="35" m="1.418|0.000|0.000|1.251"/>
      <data pos="-95.9|-370.7" frame="36" m="1.418|0.000|0.000|1.251"/>
      <data pos="-95.9|-370.7" frame="37" m="1.418|0.000|0.000|1.251"/>
      <data pos="-95.9|-370.7" frame="38" m="1.418|0.000|0.000|1.251"/>
      <data pos="-95.9|-370.7" frame="39" m="1.418|0.000|0.000|1.251"/>
      <data pos="-76.65|-370.7" frame="40" m="1.418|0.000|0.000|1.251"/>
      <data pos="-57.45|-370.7" frame="41" m="1.418|0.000|0.000|1.251"/>
      <data pos="-38.25|-370.7" frame="42" m="1.418|0.000|0.000|1.251"/>
      <data pos="-19.05|-370.7" frame="43" m="1.418|0.000|0.000|1.251"/>
      <data pos="0.1|-370.7" frame="44" m="1.418|0.000|0.000|1.251"/>
      <data pos="0.15|-370.7" frame="45" m="1.418|0.000|0.000|1.251"/>
      <data pos="0.15|-370.7" frame="46" m="1.418|0.000|0.000|1.251"/>
      <data pos="0.15|-370.7" frame="47" m="1.418|0.000|0.000|1.251"/>
      <data pos="0.15|-370.7" frame="48" m="1.418|0.000|0.000|1.251"/>
      <data pos="0.15|-370.7" frame="49" m="1.418|0.000|0.000|1.251"/>
      <data pos="0.1|-370.7" frame="50" m="1.418|0.000|0.000|1.251"/>
      <data pos="0.1|-370.7" frame="51" m="1.418|0.000|0.000|1.251"/>
      <data pos="0.1|-370.7" frame="52" m="1.418|0.000|0.000|1.251"/>
      <data pos="0.1|-370.7" frame="53" m="1.418|0.000|0.000|1.251"/>
      <data pos="0.1|-370.7" frame="54" m="1.418|0.000|0.000|1.251"/>
      <data pos="0.1|-370.7" frame="55" m="1.418|0.000|0.000|1.251"/>
      <data pos="0.1|-370.7" frame="56" m="1.418|0.000|0.000|1.251"/>
      <data pos="0.1|-370.7" frame="57" m="1.418|0.000|0.000|1.251"/>
      <data pos="0.1|-370.7" frame="58" m="1.418|0.000|0.000|1.251"/>
      <data pos="0.1|-370.7" frame="59" m="1.418|0.000|0.000|1.251"/>
      <data pos="0.1|-370.7" frame="60" m="1.418|0.000|0.000|1.251"/>
      <data pos="0.1|-370.7" frame="61" m="1.418|0.000|0.000|1.251"/>
      <data pos="0.1|-370.7" frame="62" m="1.418|0.000|0.000|1.251"/>
      <data pos="0.1|-370.7" frame="63" m="1.418|0.000|0.000|1.251"/>
      <data pos="0.1|-370.7" frame="64" m="1.418|0.000|0.000|1.251"/>
      <data pos="0.1|-370.7" frame="65" m="1.418|0.000|0.000|1.251"/>
      <data pos="0.1|-370.7" frame="66" m="1.418|0.000|0.000|1.251"/>
      <data pos="0.1|-370.7" frame="67" m="1.418|0.000|0.000|1.251"/>
      <data pos="0.1|-370.7" frame="68" m="1.418|0.000|0.000|1.251"/>
      <data pos="0.1|-370.7" frame="69" m="1.418|0.000|0.000|1.251"/>
      <data pos="0.1|-370.7" frame="70" m="1.418|0.000|0.000|1.251"/>
      <data pos="0.1|-370.7" frame="71" m="1.418|0.000|0.000|1.251"/>
      <data pos="0.1|-370.7" frame="72" m="1.418|0.000|0.000|1.251"/>
      <data pos="0.1|-370.7" frame="73" m="1.418|0.000|0.000|1.251"/>
      <data pos="0.1|-370.7" frame="74" m="1.418|0.000|0.000|1.251"/>
      <data pos="0.1|-370.7" frame="75" m="1.418|0.000|0.000|1.251"/>
      <data pos="0.1|-370.7" frame="76" m="1.418|0.000|0.000|1.251"/>
      <data pos="0.1|-370.7" frame="77" m="1.418|0.000|0.000|1.251"/>
      <data pos="0.1|-370.7" frame="78" m="1.418|0.000|0.000|1.251"/>
      <data pos="0.1|-370.7" frame="79" m="1.418|0.000|0.000|1.251"/>
      <data pos="0.1|-370.7" frame="80" m="1.418|0.000|0.000|1.251"/>
      <data pos="0.1|-370.7" frame="81" m="1.418|0.000|0.000|1.251"/>
      <data pos="0.1|-370.7" frame="82" m="1.418|0.000|0.000|1.251"/>
      <data pos="0.1|-370.7" frame="83" m="1.418|0.000|0.000|1.251"/>
      <data pos="0.1|-370.7" frame="84" m="1.418|0.000|0.000|1.251"/>
      <data pos="0.1|-370.7" frame="85" m="1.418|0.000|0.000|1.251"/>
      <data pos="0.1|-370.7" frame="86" m="1.418|0.000|0.000|1.251"/>
      <data pos="0.1|-370.7" frame="87" m="1.418|0.000|0.000|1.251"/>
      <data pos="0.1|-370.7" frame="88" m="1.418|0.000|0.000|1.251"/>
    </drop_shadow>
    <LARGE_Arm_Top_Lower_10>
      <data pos="-434.15|190.3" frame="1" m="0.001|0|0|0.001" v="0"/>
      <data pos="131.7|-52.55" frame="12" m="0.848|0.530|-0.530|0.848"/>
      <data pos="149.35|-50.15" frame="13" m="0.851|0.523|-0.523|0.851"/>
      <data pos="165.85|-48" frame="14" m="0.855|0.515|-0.515|0.855"/>
      <data pos="181.25|-45.95" frame="15" m="0.860|0.508|-0.508|0.860"/>
      <data pos="195.5|-44.05" frame="16" m="0.864|0.501|-0.501|0.864"/>
      <data pos="208.6|-42.25" frame="17" m="0.866|0.496|-0.496|0.866"/>
      <data pos="220.55|-40.75" frame="18" m="0.870|0.489|-0.489|0.870"/>
      <data pos="231.4|-39.3" frame="19" m="0.873|0.485|-0.485|0.873"/>
      <data pos="241.05|-38" frame="20" m="0.875|0.481|-0.481|0.875"/>
      <data pos="249.6|-36.85" frame="21" m="0.877|0.477|-0.477|0.877"/>
      <data pos="257.05|-35.9" frame="22" m="0.879|0.474|-0.474|0.879"/>
      <data pos="263.25|-35.05" frame="23" m="0.881|0.470|-0.470|0.881"/>
      <data pos="268.4|-34.4" frame="24" m="0.881|0.470|-0.470|0.881"/>
      <data pos="272.35|-33.85" frame="25" m="0.883|0.466|-0.466|0.883"/>
      <data pos="275.25|-33.5" frame="26" m="0.883|0.466|-0.466|0.883"/>
      <data pos="276.95|-33.25" frame="27" m="0.883|0.466|-0.466|0.883"/>
      <data pos="277.5|-33.15" frame="28" m="0.885|0.466|-0.466|0.885"/>
      <data pos="277.5|-33.15" frame="29" m="0.885|0.466|-0.466|0.885"/>
      <data pos="147.2|-64.05" frame="30" m="0.982|0.179|-0.179|0.982"/>
      <data pos="17|-70.15" frame="31" m="0.991|-0.118|0.118|0.991"/>
      <data pos="-119.3|-32.8" frame="32" m="0.909|-0.410|0.410|0.909"/>
      <data pos="-243.3|19.9" frame="33" m="0.746|-0.663|0.663|0.746"/>
      <data pos="-218.4|78" frame="34" m="0.001|0|0|0.001" v="0"/>
    </LARGE_Arm_Top_Lower_10>
    <LARGE_Arm_Top_Lower_09>
      <data pos="-278|40.4" frame="1" m="0.001|0|0|0.001" v="0"/>
      <data pos="-403.4|158.45" frame="5" m="-0.040|-0.999|0.999|-0.040"/>
      <data pos="-423.05|174.35" frame="6" m="-0.140|-0.990|0.990|-0.140"/>
      <data pos="-428.6|184.7" frame="7" m="-0.239|-0.970|0.970|-0.239"/>
      <data pos="-434.15|190.3" frame="8" m="-0.340|-0.940|0.940|-0.340"/>
      <data pos="-434.15|190.3" frame="9" m="-0.340|-0.940|0.940|-0.340"/>
      <data pos="-434.15|190.3" frame="10" m="-0.340|-0.940|0.940|-0.340"/>
      <data pos="-278|40.4" frame="11" m="0.596|-0.801|0.801|0.596"/>
      <data pos="-278|40.4" frame="12" m="0.001|0|0|0.001" v="0"/>
    </LARGE_Arm_Top_Lower_09>
    <LARGE_Arm_Back_Lower_08>
      <data pos="83.85|-73.1" frame="1" m="0.001|0|0|0.001" v="0"/>
      <data pos="-183.8|115.4" frame="5" m="-0.199|-0.814|0.970|-0.238"/>
      <data pos="-203.85|129.55" frame="6" m="-0.287|-0.774|0.936|-0.347"/>
      <data pos="-223.9|143.7" frame="7" m="-0.370|-0.724|0.889|-0.454"/>
      <data pos="-244|157.75" frame="8" m="-0.446|-0.667|0.831|-0.556"/>
      <data pos="-244|157.75" frame="9" m="-0.446|-0.667|0.831|-0.556"/>
      <data pos="-244|157.75" frame="10" m="-0.446|-0.667|0.831|-0.556"/>
      <data pos="-21.2|17.95" frame="11" m="0.600|-0.670|0.744|0.666"/>
      <data pos="-21.2|17.95" frame="12" m="0.001|0|0|0.001" v="0"/>
    </LARGE_Arm_Back_Lower_08>
    <LARGE_Arm_Back_Lower_10>
      <data pos="24.6|-48.35" frame="1" m="0.001|0|0|0.001" v="0"/>
      <data pos="201.6|-3.4" frame="12" m="0.972|0.235|-0.235|0.972"/>
      <data pos="220.55|-0.65" frame="13" m="0.972|0.234|-0.234|0.972"/>
      <data pos="238.3|2" frame="14" m="0.972|0.230|-0.230|0.972"/>
      <data pos="254.85|4.45" frame="15" m="0.972|0.230|-0.230|0.972"/>
      <data pos="270.1|6.7" frame="16" m="0.972|0.230|-0.230|0.972"/>
      <data pos="284.15|8.8" frame="17" m="0.972|0.230|-0.230|0.972"/>
      <data pos="297|10.75" frame="18" m="0.973|0.229|-0.229|0.973"/>
      <data pos="308.6|12.45" frame="19" m="0.973|0.226|-0.226|0.973"/>
      <data pos="319|14" frame="20" m="0.973|0.226|-0.226|0.973"/>
      <data pos="328.2|15.35" frame="21" m="0.973|0.226|-0.226|0.973"/>
      <data pos="336.15|16.5" frame="22" m="0.973|0.226|-0.226|0.973"/>
      <data pos="342.8|17.55" frame="23" m="0.973|0.225|-0.225|0.973"/>
      <data pos="348.3|18.3" frame="24" m="0.973|0.225|-0.225|0.973"/>
      <data pos="352.6|18.95" frame="25" m="0.973|0.225|-0.225|0.973"/>
      <data pos="355.65|19.45" frame="26" m="0.973|0.225|-0.225|0.973"/>
      <data pos="357.5|19.7" frame="27" m="0.974|0.225|-0.225|0.974"/>
      <data pos="358.15|19.8" frame="28" m="0.974|0.226|-0.226|0.974"/>
      <data pos="358.15|19.8" frame="29" m="0.974|0.226|-0.226|0.974"/>
      <data pos="284.45|-24.9" frame="30" m="0.998|0.048|-0.048|0.998"/>
      <data pos="210.75|-52.95" frame="31" m="0.990|-0.131|0.131|0.990"/>
      <data pos="112.15|-64.45" frame="32" m="0.949|-0.309|0.309|0.949"/>
      <data pos="24.6|-48.35" frame="33" m="0.877|-0.478|0.478|0.877"/>
      <data pos="24.6|-48.35" frame="34" m="0.001|0|0|0.001" v="0"/>
    </LARGE_Arm_Back_Lower_10>
    <LARGE_Arm_Back_Upper_01>
      <data pos="93.6|87.45" frame="1" m="0.972|-0.237|0.237|0.972"/>
      <data pos="39.15|115.4" frame="2" m="0.841|-0.538|0.523|0.818"/>
      <data pos="-7|139.1" frame="3" m="0.657|-0.752|0.714|0.624"/>
      <data pos="-44.65|158.45" frame="4" m="0.469|-0.881|0.820|0.437"/>
      <data pos="-74|173.55" frame="5" m="0.305|-0.951|0.871|0.279"/>
      <data pos="-94.95|184.25" frame="6" m="0.179|-0.983|0.890|0.162"/>
      <data pos="-107.45|190.7" frame="7" m="0.105|-0.994|0.894|0.094"/>
      <data pos="-111.7|192.8" frame="8" m="0.080|-0.997|0.894|0.072"/>
      <data pos="-111.7|192.8" frame="9" m="0.080|-0.997|0.894|0.072"/>
      <data pos="-111.7|192.8" frame="10" m="0.080|-0.997|0.894|0.072"/>
      <data pos="17|152.5" frame="11" m="0.827|-0.560|0.531|0.784"/>
      <data pos="145.65|112.25" frame="12" m="0.956|0.294|-0.294|0.956"/>
      <data pos="156.55|112.6" frame="13" m="0.937|0.347|-0.347|0.937"/>
      <data pos="166.75|113" frame="14" m="0.916|0.399|-0.399|0.916"/>
      <data pos="176.3|113.3" frame="15" m="0.895|0.443|-0.443|0.895"/>
      <data pos="185.05|113.65" frame="16" m="0.873|0.485|-0.485|0.873"/>
      <data pos="193.2|114" frame="17" m="0.851|0.523|-0.523|0.851"/>
      <data pos="200.5|114.3" frame="18" m="0.829|0.556|-0.556|0.829"/>
      <data pos="207.25|114.45" frame="19" m="0.809|0.585|-0.585|0.809"/>
      <data pos="213.25|114.7" frame="20" m="0.791|0.609|-0.609|0.791"/>
      <data pos="218.5|114.9" frame="21" m="0.772|0.633|-0.633|0.772"/>
      <data pos="223.1|115.05" frame="22" m="0.758|0.650|-0.650|0.758"/>
      <data pos="226.9|115.2" frame="23" m="0.743|0.666|-0.666|0.743"/>
      <data pos="230|115.35" frame="24" m="0.732|0.679|-0.679|0.732"/>
      <data pos="232.6|115.4" frame="25" m="0.723|0.689|-0.689|0.723"/>
      <data pos="234.35|115.45" frame="26" m="0.717|0.695|-0.695|0.717"/>
      <data pos="235.4|115.5" frame="27" m="0.713|0.698|-0.698|0.713"/>
      <data pos="235.7|115.5" frame="28" m="0.713|0.701|-0.701|0.713"/>
      <data pos="235.7|115.5" frame="29" m="0.713|0.701|-0.701|0.713"/>
      <data pos="195.6|106.3" frame="30" m="0.901|0.431|-0.431|0.901"/>
      <data pos="155.6|97.1" frame="31" m="0.993|0.114|-0.114|0.993"/>
      <data pos="115.6|87.85" frame="32" m="0.977|-0.209|0.209|0.977"/>
      <data pos="75.6|78.55" frame="33" m="0.855|-0.515|0.515|0.855"/>
      <data pos="35.55|69.3" frame="34" m="0.642|-0.766|0.766|0.642"/>
      <data pos="35.55|69.3" frame="35" m="0.642|-0.766|0.766|0.642"/>
      <data pos="35.55|69.3" frame="36" m="0.642|-0.766|0.766|0.642"/>
      <data pos="35.55|69.3" frame="37" m="0.642|-0.766|0.766|0.642"/>
      <data pos="35.55|69.3" frame="38" m="0.642|-0.766|0.766|0.642"/>
      <data pos="35.55|69.3" frame="39" m="0.642|-0.766|0.766|0.642"/>
      <data pos="45.35|73.9" frame="40" m="0.732|-0.679|0.679|0.732"/>
      <data pos="55.1|78.4" frame="41" m="0.812|-0.581|0.581|0.812"/>
      <data pos="65|82.9" frame="42" m="0.881|-0.470|0.470|0.881"/>
      <data pos="74.75|87.4" frame="43" m="0.934|-0.355|0.355|0.934"/>
      <data pos="84.6|91.95" frame="44" m="0.972|-0.237|0.237|0.972"/>
      <data pos="86.1|91.2" frame="45" m="0.971|-0.234|0.234|0.971"/>
      <data pos="87.6|90.45" frame="46" m="0.971|-0.234|0.234|0.971"/>
      <data pos="89.1|89.7" frame="47" m="0.971|-0.234|0.234|0.971"/>
      <data pos="90.6|88.95" frame="48" m="0.971|-0.234|0.234|0.971"/>
      <data pos="92.1|88.2" frame="49" m="0.971|-0.234|0.234|0.971"/>
      <data pos="93.6|87.45" frame="50" m="0.972|-0.237|0.237|0.972"/>
      <data pos="93.6|87.45" frame="51" m="0.972|-0.237|0.237|0.972"/>
      <data pos="93.6|87.45" frame="52" m="0.972|-0.237|0.237|0.972"/>
      <data pos="93.6|87.45" frame="53" m="0.972|-0.237|0.237|0.972"/>
      <data pos="93.6|87.45" frame="54" m="0.972|-0.237|0.237|0.972"/>
      <data pos="93.6|87.45" frame="55" m="0.972|-0.237|0.237|0.972"/>
      <data pos="93.6|87.45" frame="56" m="0.972|-0.237|0.237|0.972"/>
      <data pos="93.6|87.45" frame="57" m="0.972|-0.237|0.237|0.972"/>
      <data pos="93.6|87.45" frame="58" m="0.972|-0.237|0.237|0.972"/>
      <data pos="93.6|87.45" frame="59" m="0.972|-0.237|0.237|0.972"/>
      <data pos="93.6|87.45" frame="60" m="0.972|-0.237|0.237|0.972"/>
      <data pos="93.6|87.45" frame="61" m="0.972|-0.237|0.237|0.972"/>
      <data pos="93.6|87.45" frame="62" m="0.972|-0.237|0.237|0.972"/>
      <data pos="93.6|87.45" frame="63" m="0.972|-0.237|0.237|0.972"/>
      <data pos="93.6|87.45" frame="64" m="0.972|-0.237|0.237|0.972"/>
      <data pos="93.6|87.45" frame="65" m="0.972|-0.237|0.237|0.972"/>
      <data pos="93.6|87.45" frame="66" m="0.972|-0.237|0.237|0.972"/>
      <data pos="93.6|87.45" frame="67" m="0.972|-0.237|0.237|0.972"/>
      <data pos="93.6|87.45" frame="68" m="0.972|-0.237|0.237|0.972"/>
      <data pos="93.6|87.45" frame="69" m="0.972|-0.237|0.237|0.972"/>
      <data pos="93.6|87.45" frame="70" m="0.972|-0.237|0.237|0.972"/>
      <data pos="93.6|87.45" frame="71" m="0.972|-0.237|0.237|0.972"/>
      <data pos="93.6|87.45" frame="72" m="0.972|-0.237|0.237|0.972"/>
      <data pos="93.6|87.45" frame="73" m="0.972|-0.237|0.237|0.972"/>
      <data pos="93.6|87.45" frame="74" m="0.972|-0.237|0.237|0.972"/>
      <data pos="93.6|87.45" frame="75" m="0.972|-0.237|0.237|0.972"/>
      <data pos="93.6|87.45" frame="76" m="0.972|-0.237|0.237|0.972"/>
      <data pos="93.6|87.45" frame="77" m="0.972|-0.237|0.237|0.972"/>
      <data pos="93.6|87.45" frame="78" m="0.972|-0.237|0.237|0.972"/>
      <data pos="93.6|87.45" frame="79" m="0.972|-0.237|0.237|0.972"/>
      <data pos="93.6|87.45" frame="80" m="0.972|-0.237|0.237|0.972"/>
      <data pos="93.6|87.45" frame="81" m="0.972|-0.237|0.237|0.972"/>
      <data pos="93.6|87.45" frame="82" m="0.972|-0.237|0.237|0.972"/>
      <data pos="93.6|87.45" frame="83" m="0.972|-0.237|0.237|0.972"/>
      <data pos="93.6|87.45" frame="84" m="0.972|-0.237|0.237|0.972"/>
      <data pos="93.6|87.45" frame="85" m="0.972|-0.237|0.237|0.972"/>
      <data pos="93.6|87.45" frame="86" m="0.972|-0.237|0.237|0.972"/>
      <data pos="93.6|87.45" frame="87" m="0.972|-0.237|0.237|0.972"/>
      <data pos="93.6|87.45" frame="88" m="0.972|-0.237|0.237|0.972"/>
    </LARGE_Arm_Back_Upper_01>
    <LARGE_Arm_Back_Lower_01>
      <data pos="83.85|-73.1" frame="1" m="0.967|-0.254|0.254|0.967"/>
      <data pos="-55.5|25.15" frame="2" m="0.441|-0.801|0.874|0.482"/>
      <data pos="-139.15|84.05" frame="3" m="0.016|-0.864|0.999|0.018"/>
      <data pos="-167|103.65" frame="4" m="-0.119|-0.839|0.989|-0.140"/>
      <data pos="-183.8|115.4" frame="5" m="0.001|0|0|0.001" v="0"/>
      <data pos="-58.8|-65.3" frame="34" m="0.776|-0.631|0.631|0.776"/>
      <data pos="-58.8|-65.3" frame="35" m="0.776|-0.631|0.631|0.776"/>
      <data pos="-58.8|-65.3" frame="36" m="0.776|-0.631|0.631|0.776"/>
      <data pos="-58.8|-65.3" frame="37" m="0.776|-0.631|0.631|0.776"/>
      <data pos="-58.8|-65.3" frame="38" m="0.776|-0.631|0.631|0.776"/>
      <data pos="-58.8|-65.3" frame="39" m="0.776|-0.631|0.631|0.776"/>
      <data pos="-32.05|-65.9" frame="40" m="0.827|-0.560|0.560|0.827"/>
      <data pos="-5.35|-66.55" frame="41" m="0.871|-0.489|0.489|0.871"/>
      <data pos="21.4|-67.25" frame="42" m="0.910|-0.412|0.412|0.910"/>
      <data pos="48.15|-67.9" frame="43" m="0.941|-0.334|0.334|0.941"/>
      <data pos="74.85|-68.6" frame="44" m="0.967|-0.254|0.254|0.967"/>
      <data pos="76.35|-69.3" frame="45" m="0.967|-0.251|0.251|0.967"/>
      <data pos="77.85|-70.05" frame="46" m="0.967|-0.251|0.251|0.967"/>
      <data pos="79.35|-70.8" frame="47" m="0.967|-0.251|0.251|0.967"/>
      <data pos="80.85|-71.55" frame="48" m="0.967|-0.251|0.251|0.967"/>
      <data pos="82.35|-72.3" frame="49" m="0.967|-0.251|0.251|0.967"/>
      <data pos="83.85|-73.1" frame="50" m="0.967|-0.254|0.254|0.967"/>
      <data pos="83.85|-73.1" frame="51" m="0.967|-0.254|0.254|0.967"/>
      <data pos="83.85|-73.1" frame="52" m="0.967|-0.254|0.254|0.967"/>
      <data pos="83.85|-73.1" frame="53" m="0.967|-0.254|0.254|0.967"/>
      <data pos="83.85|-73.1" frame="54" m="0.967|-0.254|0.254|0.967"/>
      <data pos="83.85|-73.1" frame="55" m="0.967|-0.254|0.254|0.967"/>
      <data pos="83.85|-73.1" frame="56" m="0.967|-0.254|0.254|0.967"/>
      <data pos="83.85|-73.1" frame="57" m="0.967|-0.254|0.254|0.967"/>
      <data pos="83.85|-73.1" frame="58" m="0.967|-0.254|0.254|0.967"/>
      <data pos="83.85|-73.1" frame="59" m="0.967|-0.254|0.254|0.967"/>
      <data pos="83.85|-73.1" frame="60" m="0.967|-0.254|0.254|0.967"/>
      <data pos="83.85|-73.1" frame="61" m="0.967|-0.254|0.254|0.967"/>
      <data pos="83.85|-73.1" frame="62" m="0.967|-0.254|0.254|0.967"/>
      <data pos="83.85|-73.1" frame="63" m="0.967|-0.254|0.254|0.967"/>
      <data pos="83.85|-73.1" frame="64" m="0.967|-0.254|0.254|0.967"/>
      <data pos="83.85|-73.1" frame="65" m="0.967|-0.254|0.254|0.967"/>
      <data pos="83.85|-73.1" frame="66" m="0.967|-0.254|0.254|0.967"/>
      <data pos="83.85|-73.1" frame="67" m="0.967|-0.254|0.254|0.967"/>
      <data pos="83.85|-73.1" frame="68" m="0.967|-0.254|0.254|0.967"/>
      <data pos="83.85|-73.1" frame="69" m="0.967|-0.254|0.254|0.967"/>
      <data pos="83.85|-73.1" frame="70" m="0.967|-0.254|0.254|0.967"/>
      <data pos="83.85|-73.1" frame="71" m="0.967|-0.254|0.254|0.967"/>
      <data pos="83.85|-73.1" frame="72" m="0.967|-0.254|0.254|0.967"/>
      <data pos="83.85|-73.1" frame="73" m="0.967|-0.254|0.254|0.967"/>
      <data pos="83.85|-73.1" frame="74" m="0.967|-0.254|0.254|0.967"/>
      <data pos="83.85|-73.1" frame="75" m="0.967|-0.254|0.254|0.967"/>
      <data pos="83.85|-73.1" frame="76" m="0.967|-0.254|0.254|0.967"/>
      <data pos="83.85|-73.1" frame="77" m="0.967|-0.254|0.254|0.967"/>
      <data pos="83.85|-73.1" frame="78" m="0.967|-0.254|0.254|0.967"/>
      <data pos="83.85|-73.1" frame="79" m="0.967|-0.254|0.254|0.967"/>
      <data pos="83.85|-73.1" frame="80" m="0.967|-0.254|0.254|0.967"/>
      <data pos="83.85|-73.1" frame="81" m="0.967|-0.254|0.254|0.967"/>
      <data pos="83.85|-73.1" frame="82" m="0.967|-0.254|0.254|0.967"/>
      <data pos="83.85|-73.1" frame="83" m="0.967|-0.254|0.254|0.967"/>
      <data pos="83.85|-73.1" frame="84" m="0.967|-0.254|0.254|0.967"/>
      <data pos="83.85|-73.1" frame="85" m="0.967|-0.254|0.254|0.967"/>
      <data pos="83.85|-73.1" frame="86" m="0.967|-0.254|0.254|0.967"/>
      <data pos="83.85|-73.1" frame="87" m="0.967|-0.254|0.254|0.967"/>
      <data pos="83.85|-73.1" frame="88" m="0.967|-0.254|0.254|0.967"/>
    </LARGE_Arm_Back_Lower_01>
    <LARGE_Arm_Back_Lower_06>
      <data pos="83.85|-73.1" frame="1" m="0.001|0|0|0.001" v="0"/>
      <data pos="-183.8|115.4" frame="5" m="-0.199|-0.814|0.970|-0.238"/>
      <data pos="-203.85|129.55" frame="6" m="-0.287|-0.774|0.936|-0.347"/>
      <data pos="-223.9|143.7" frame="7" m="-0.370|-0.724|0.889|-0.454"/>
      <data pos="-244|157.75" frame="8" m="-0.446|-0.667|0.831|-0.556"/>
      <data pos="-244|157.75" frame="9" m="-0.446|-0.667|0.831|-0.556"/>
      <data pos="-244|157.75" frame="10" m="-0.446|-0.667|0.831|-0.556"/>
      <data pos="-21.2|17.95" frame="11" m="0.600|-0.670|0.744|0.666"/>
      <data pos="-21.2|17.95" frame="12" m="0.001|0|0|0.001" v="0"/>
    </LARGE_Arm_Back_Lower_06>
    <LARGE_Arm_Back_Lower_07>
      <data pos="24.6|-48.35" frame="1" m="0.001|0|0|0.001" v="0"/>
      <data pos="201.6|-3.4" frame="12" m="0.972|0.235|-0.235|0.972"/>
      <data pos="220.55|-0.65" frame="13" m="0.972|0.234|-0.234|0.972"/>
      <data pos="238.3|2" frame="14" m="0.972|0.230|-0.230|0.972"/>
      <data pos="254.85|4.45" frame="15" m="0.972|0.230|-0.230|0.972"/>
      <data pos="270.1|6.7" frame="16" m="0.972|0.230|-0.230|0.972"/>
      <data pos="284.15|8.8" frame="17" m="0.972|0.230|-0.230|0.972"/>
      <data pos="297|10.75" frame="18" m="0.973|0.229|-0.229|0.973"/>
      <data pos="308.6|12.45" frame="19" m="0.973|0.226|-0.226|0.973"/>
      <data pos="319|14" frame="20" m="0.973|0.226|-0.226|0.973"/>
      <data pos="328.2|15.35" frame="21" m="0.973|0.226|-0.226|0.973"/>
      <data pos="336.15|16.5" frame="22" m="0.973|0.226|-0.226|0.973"/>
      <data pos="342.8|17.55" frame="23" m="0.973|0.225|-0.225|0.973"/>
      <data pos="348.3|18.3" frame="24" m="0.973|0.225|-0.225|0.973"/>
      <data pos="352.6|18.95" frame="25" m="0.973|0.225|-0.225|0.973"/>
      <data pos="355.65|19.45" frame="26" m="0.973|0.225|-0.225|0.973"/>
      <data pos="357.5|19.7" frame="27" m="0.974|0.225|-0.225|0.974"/>
      <data pos="358.15|19.8" frame="28" m="0.974|0.226|-0.226|0.974"/>
      <data pos="358.15|19.8" frame="29" m="0.974|0.226|-0.226|0.974"/>
      <data pos="284.45|-24.9" frame="30" m="0.998|0.048|-0.048|0.998"/>
      <data pos="210.75|-52.95" frame="31" m="0.990|-0.131|0.131|0.990"/>
      <data pos="112.15|-64.45" frame="32" m="0.949|-0.309|0.309|0.949"/>
      <data pos="24.6|-48.35" frame="33" m="0.877|-0.478|0.478|0.877"/>
      <data pos="24.6|-48.35" frame="34" m="0.001|0|0|0.001" v="0"/>
    </LARGE_Arm_Back_Lower_07>
    <LARGE_Leg_Back_Lower_01>
      <data pos="141.2|-184.55" frame="1" m="1.000|0.000|0.111|1.000"/>
      <data pos="127.45|-173.55" frame="2" m="1.010|0.000|0.030|1.088"/>
      <data pos="115.9|-164.15" frame="3" m="1.019|0.000|-0.041|1.157"/>
      <data pos="106.35|-156.55" frame="4" m="1.026|0.000|-0.112|1.209"/>
      <data pos="98.95|-150.65" frame="5" m="1.032|0.000|-0.170|1.247"/>
      <data pos="93.7|-146.4" frame="6" m="1.036|0.000|-0.214|1.272"/>
      <data pos="90.5|-143.9" frame="7" m="1.038|0.000|-0.240|1.287"/>
      <data pos="89.45|-143.05" frame="8" m="1.039|0.000|-0.252|1.292"/>
      <data pos="89.45|-143.05" frame="9" m="1.039|0.000|-0.252|1.292"/>
      <data pos="89.45|-143.05" frame="10" m="1.039|0.000|-0.252|1.292"/>
      <data pos="128.55|-150" frame="11" m="1.039|0.000|-0.226|1.246"/>
      <data pos="167.5|-156.85" frame="12" m="1.039|0.000|-0.205|1.202"/>
      <data pos="172.5|-157.3" frame="13" m="1.039|0.000|-0.176|1.203"/>
      <data pos="177.2|-157.7" frame="14" m="1.039|0.000|-0.154|1.205"/>
      <data pos="181.55|-158.05" frame="15" m="1.039|0.000|-0.132|1.205"/>
      <data pos="185.6|-158.35" frame="16" m="1.039|0.000|-0.111|1.206"/>
      <data pos="189.3|-158.7" frame="17" m="1.039|0.000|-0.090|1.206"/>
      <data pos="192.7|-159" frame="18" m="1.039|0.000|-0.074|1.206"/>
      <data pos="195.75|-159.25" frame="19" m="1.039|0.000|-0.058|1.205"/>
      <data pos="198.55|-159.45" frame="20" m="1.039|0.000|-0.043|1.205"/>
      <data pos="200.95|-159.65" frame="21" m="1.039|0.000|-0.032|1.204"/>
      <data pos="203.05|-159.9" frame="22" m="1.039|0.000|-0.021|1.204"/>
      <data pos="204.85|-160" frame="23" m="1.039|0.000|-0.011|1.203"/>
      <data pos="206.25|-160.2" frame="24" m="1.039|0.000|-0.001|1.203"/>
      <data pos="207.4|-160.3" frame="25" m="1.039|0.000|0.000|1.202"/>
      <data pos="208.2|-160.35" frame="26" m="1.039|0.000|0.005|1.202"/>
      <data pos="208.7|-160.4" frame="27" m="1.039|0.000|0.006|1.202"/>
      <data pos="208.85|-160.4" frame="28" m="1.039|0.000|0.009|1.202"/>
      <data pos="208.85|-160.4" frame="29" m="1.039|0.000|0.009|1.202"/>
      <data pos="183.55|-165.3" frame="30" m="1.031|0.000|-0.052|1.167"/>
      <data pos="158.3|-170" frame="31" m="1.023|0.000|-0.114|1.129"/>
      <data pos="132.95|-174.9" frame="32" m="1.016|0.000|-0.168|1.088"/>
      <data pos="107.75|-179.7" frame="33" m="1.008|0.000|-0.218|1.045"/>
      <data pos="82.45|-184.55" frame="34" m="1.000|0.000|-0.268|1.000"/>
      <data pos="82.45|-184.55" frame="35" m="1.000|0.000|-0.268|1.000"/>
      <data pos="82.45|-184.55" frame="36" m="1.000|0.000|-0.268|1.000"/>
      <data pos="82.45|-184.55" frame="37" m="1.000|0.000|-0.268|1.000"/>
      <data pos="82.45|-184.55" frame="38" m="1.000|0.000|-0.268|1.000"/>
      <data pos="82.45|-184.55" frame="39" m="1.000|0.000|-0.268|1.000"/>
      <data pos="94.65|-184.55" frame="40" m="1.000|0.000|-0.188|1.012"/>
      <data pos="106.85|-184.55" frame="41" m="1.000|0.000|-0.108|1.018"/>
      <data pos="119|-184.55" frame="42" m="1.000|0.000|-0.028|1.018"/>
      <data pos="131.25|-184.55" frame="43" m="1.000|0.000|0.045|1.012"/>
      <data pos="143.45|-184.55" frame="44" m="1.000|0.000|0.126|1.000"/>
      <data pos="143.1|-184.55" frame="45" m="1.000|0.000|0.123|1.000"/>
      <data pos="142.7|-184.55" frame="46" m="1.000|0.000|0.119|1.000"/>
      <data pos="142.35|-184.55" frame="47" m="1.000|0.000|0.118|1.000"/>
      <data pos="141.95|-184.55" frame="48" m="1.000|0.000|0.114|1.000"/>
      <data pos="141.6|-184.55" frame="49" m="1.000|0.000|0.111|1.000"/>
      <data pos="141.2|-184.55" frame="50" m="1.000|0.000|0.111|1.000"/>
      <data pos="141.2|-184.55" frame="51" m="1.000|0.000|0.111|1.000"/>
      <data pos="141.2|-184.55" frame="52" m="1.000|0.000|0.111|1.000"/>
      <data pos="141.2|-184.55" frame="53" m="1.000|0.000|0.111|1.000"/>
      <data pos="141.2|-184.55" frame="54" m="1.000|0.000|0.111|1.000"/>
      <data pos="141.2|-184.55" frame="55" m="1.000|0.000|0.111|1.000"/>
      <data pos="141.2|-184.55" frame="56" m="1.000|0.000|0.111|1.000"/>
      <data pos="141.2|-184.55" frame="57" m="1.000|0.000|0.111|1.000"/>
      <data pos="141.2|-184.55" frame="58" m="1.000|0.000|0.111|1.000"/>
      <data pos="141.2|-184.55" frame="59" m="1.000|0.000|0.111|1.000"/>
      <data pos="141.2|-184.55" frame="60" m="1.000|0.000|0.111|1.000"/>
      <data pos="141.2|-184.55" frame="61" m="1.000|0.000|0.111|1.000"/>
      <data pos="141.2|-184.55" frame="62" m="1.000|0.000|0.111|1.000"/>
      <data pos="141.2|-184.55" frame="63" m="1.000|0.000|0.111|1.000"/>
      <data pos="141.2|-184.55" frame="64" m="1.000|0.000|0.111|1.000"/>
      <data pos="141.2|-184.55" frame="65" m="1.000|0.000|0.111|1.000"/>
      <data pos="141.2|-184.55" frame="66" m="1.000|0.000|0.111|1.000"/>
      <data pos="141.2|-184.55" frame="67" m="1.000|0.000|0.111|1.000"/>
      <data pos="141.2|-184.55" frame="68" m="1.000|0.000|0.111|1.000"/>
      <data pos="141.2|-184.55" frame="69" m="1.000|0.000|0.111|1.000"/>
      <data pos="141.2|-184.55" frame="70" m="1.000|0.000|0.111|1.000"/>
      <data pos="141.2|-184.55" frame="71" m="1.000|0.000|0.111|1.000"/>
      <data pos="141.2|-184.55" frame="72" m="1.000|0.000|0.111|1.000"/>
      <data pos="141.2|-184.55" frame="73" m="1.000|0.000|0.111|1.000"/>
      <data pos="141.2|-184.55" frame="74" m="1.000|0.000|0.111|1.000"/>
      <data pos="141.2|-184.55" frame="75" m="1.000|0.000|0.111|1.000"/>
      <data pos="141.2|-184.55" frame="76" m="1.000|0.000|0.111|1.000"/>
      <data pos="141.2|-184.55" frame="77" m="1.000|0.000|0.111|1.000"/>
      <data pos="141.2|-184.55" frame="78" m="1.000|0.000|0.111|1.000"/>
      <data pos="141.2|-184.55" frame="79" m="1.000|0.000|0.111|1.000"/>
      <data pos="141.2|-184.55" frame="80" m="1.000|0.000|0.111|1.000"/>
      <data pos="141.2|-184.55" frame="81" m="1.000|0.000|0.111|1.000"/>
      <data pos="141.2|-184.55" frame="82" m="1.000|0.000|0.111|1.000"/>
      <data pos="141.2|-184.55" frame="83" m="1.000|0.000|0.111|1.000"/>
      <data pos="141.2|-184.55" frame="84" m="1.000|0.000|0.111|1.000"/>
      <data pos="141.2|-184.55" frame="85" m="1.000|0.000|0.111|1.000"/>
      <data pos="141.2|-184.55" frame="86" m="1.000|0.000|0.111|1.000"/>
      <data pos="141.2|-184.55" frame="87" m="1.000|0.000|0.111|1.000"/>
      <data pos="141.2|-184.55" frame="88" m="1.000|0.000|0.111|1.000"/>
    </LARGE_Leg_Back_Lower_01>
    <LARGE_Leg_Back_Upper_01>
      <data pos="16.25|-114.6" frame="1" m="0.989|0.148|-0.148|0.989"/>
      <data pos="2.1|-104.35" frame="2" m="0.997|0.154|-0.161|1.043"/>
      <data pos="-9.9|-95.65" frame="3" m="1.005|0.156|-0.174|1.089"/>
      <data pos="-19.7|-88.6" frame="4" m="1.010|0.161|-0.188|1.125"/>
      <data pos="-27.35|-83.1" frame="5" m="1.014|0.166|-0.194|1.155"/>
      <data pos="-32.75|-79.2" frame="6" m="1.018|0.167|-0.203|1.175"/>
      <data pos="-36|-76.85" frame="7" m="1.020|0.167|-0.205|1.187"/>
      <data pos="-37.15|-76.05" frame="8" m="1.021|0.171|-0.210|1.192"/>
      <data pos="-37.15|-76.05" frame="9" m="1.021|0.171|-0.210|1.192"/>
      <data pos="-37.15|-76.05" frame="10" m="1.021|0.171|-0.210|1.192"/>
      <data pos="-11.9|-90.55" frame="11" m="0.988|0.303|-0.343|1.083"/>
      <data pos="13.55|-105.15" frame="12" m="0.940|0.433|-0.454|0.963"/>
      <data pos="18.6|-106.15" frame="13" m="0.938|0.433|-0.454|0.961"/>
      <data pos="23.3|-107.2" frame="14" m="0.938|0.434|-0.455|0.961"/>
      <data pos="27.7|-108.1" frame="15" m="0.938|0.434|-0.455|0.961"/>
      <data pos="31.75|-108.95" frame="16" m="0.938|0.434|-0.455|0.961"/>
      <data pos="35.55|-109.7" frame="17" m="0.938|0.434|-0.455|0.961"/>
      <data pos="38.95|-110.4" frame="18" m="0.936|0.437|-0.459|0.960"/>
      <data pos="42|-111.05" frame="19" m="0.936|0.438|-0.459|0.959"/>
      <data pos="44.8|-111.65" frame="20" m="0.936|0.438|-0.459|0.959"/>
      <data pos="47.3|-112.15" frame="21" m="0.936|0.438|-0.459|0.959"/>
      <data pos="49.4|-112.6" frame="22" m="0.936|0.438|-0.459|0.959"/>
      <data pos="51.15|-112.95" frame="23" m="0.936|0.438|-0.459|0.959"/>
      <data pos="52.6|-113.25" frame="24" m="0.936|0.438|-0.459|0.959"/>
      <data pos="53.75|-113.5" frame="25" m="0.936|0.438|-0.459|0.959"/>
      <data pos="54.55|-113.65" frame="26" m="0.936|0.438|-0.459|0.959"/>
      <data pos="55.05|-113.75" frame="27" m="0.936|0.438|-0.459|0.959"/>
      <data pos="55.2|-113.85" frame="28" m="0.936|0.441|-0.462|0.959"/>
      <data pos="55.2|-113.85" frame="29" m="0.936|0.441|-0.462|0.959"/>
      <data pos="33.5|-115.35" frame="30" m="0.943|0.406|-0.420|0.963"/>
      <data pos="11.8|-117" frame="31" m="0.950|0.370|-0.381|0.965"/>
      <data pos="-9.95|-118.55" frame="32" m="0.956|0.335|-0.343|0.966"/>
      <data pos="-31.65|-120.15" frame="33" m="0.960|0.299|-0.305|0.965"/>
      <data pos="-53.4|-121.8" frame="34" m="0.964|0.267|-0.267|0.964"/>
      <data pos="-53.4|-121.8" frame="35" m="0.964|0.267|-0.267|0.964"/>
      <data pos="-53.4|-121.8" frame="36" m="0.964|0.267|-0.267|0.964"/>
      <data pos="-53.4|-121.8" frame="37" m="0.964|0.267|-0.267|0.964"/>
      <data pos="-53.4|-121.8" frame="38" m="0.964|0.267|-0.267|0.964"/>
      <data pos="-53.4|-121.8" frame="39" m="0.964|0.267|-0.267|0.964"/>
      <data pos="-37.6|-118.55" frame="40" m="0.972|0.230|-0.230|0.972"/>
      <data pos="-21.9|-115.3" frame="41" m="0.980|0.195|-0.195|0.980"/>
      <data pos="-6.2|-112.1" frame="42" m="0.987|0.157|-0.157|0.987"/>
      <data pos="9.5|-108.85" frame="43" m="0.992|0.122|-0.122|0.992"/>
      <data pos="25.25|-105.6" frame="44" m="0.996|0.087|-0.087|0.996"/>
      <data pos="23.8|-107.1" frame="45" m="0.995|0.096|-0.096|0.995"/>
      <data pos="22.3|-108.65" frame="46" m="0.994|0.105|-0.105|0.994"/>
      <data pos="20.8|-110.05" frame="47" m="0.993|0.114|-0.114|0.993"/>
      <data pos="19.25|-111.55" frame="48" m="0.992|0.127|-0.127|0.992"/>
      <data pos="17.75|-113.1" frame="49" m="0.990|0.136|-0.136|0.990"/>
      <data pos="16.25|-114.6" frame="50" m="0.989|0.148|-0.148|0.989"/>
      <data pos="16.25|-114.6" frame="51" m="0.989|0.148|-0.148|0.989"/>
      <data pos="16.25|-114.6" frame="52" m="0.989|0.148|-0.148|0.989"/>
      <data pos="16.25|-114.6" frame="53" m="0.989|0.148|-0.148|0.989"/>
      <data pos="16.25|-114.6" frame="54" m="0.989|0.148|-0.148|0.989"/>
      <data pos="16.25|-114.6" frame="55" m="0.989|0.148|-0.148|0.989"/>
      <data pos="16.25|-114.6" frame="56" m="0.989|0.148|-0.148|0.989"/>
      <data pos="16.25|-114.6" frame="57" m="0.989|0.148|-0.148|0.989"/>
      <data pos="16.25|-114.6" frame="58" m="0.989|0.148|-0.148|0.989"/>
      <data pos="16.25|-114.6" frame="59" m="0.989|0.148|-0.148|0.989"/>
      <data pos="16.25|-114.6" frame="60" m="0.989|0.148|-0.148|0.989"/>
      <data pos="16.25|-114.6" frame="61" m="0.989|0.148|-0.148|0.989"/>
      <data pos="16.25|-114.6" frame="62" m="0.989|0.148|-0.148|0.989"/>
      <data pos="16.25|-114.6" frame="63" m="0.989|0.148|-0.148|0.989"/>
      <data pos="16.25|-114.6" frame="64" m="0.989|0.148|-0.148|0.989"/>
      <data pos="16.25|-114.6" frame="65" m="0.989|0.148|-0.148|0.989"/>
      <data pos="16.25|-114.6" frame="66" m="0.989|0.148|-0.148|0.989"/>
      <data pos="16.25|-114.6" frame="67" m="0.989|0.148|-0.148|0.989"/>
      <data pos="16.25|-114.6" frame="68" m="0.989|0.148|-0.148|0.989"/>
      <data pos="16.25|-114.6" frame="69" m="0.989|0.148|-0.148|0.989"/>
      <data pos="16.25|-114.6" frame="70" m="0.989|0.148|-0.148|0.989"/>
      <data pos="16.25|-114.6" frame="71" m="0.989|0.148|-0.148|0.989"/>
      <data pos="16.25|-114.6" frame="72" m="0.989|0.148|-0.148|0.989"/>
      <data pos="16.25|-114.6" frame="73" m="0.989|0.148|-0.148|0.989"/>
      <data pos="16.25|-114.6" frame="74" m="0.989|0.148|-0.148|0.989"/>
      <data pos="16.25|-114.6" frame="75" m="0.989|0.148|-0.148|0.989"/>
      <data pos="16.25|-114.6" frame="76" m="0.989|0.148|-0.148|0.989"/>
      <data pos="16.25|-114.6" frame="77" m="0.989|0.148|-0.148|0.989"/>
      <data pos="16.25|-114.6" frame="78" m="0.989|0.148|-0.148|0.989"/>
      <data pos="16.25|-114.6" frame="79" m="0.989|0.148|-0.148|0.989"/>
      <data pos="16.25|-114.6" frame="80" m="0.989|0.148|-0.148|0.989"/>
      <data pos="16.25|-114.6" frame="81" m="0.989|0.148|-0.148|0.989"/>
      <data pos="16.25|-114.6" frame="82" m="0.989|0.148|-0.148|0.989"/>
      <data pos="16.25|-114.6" frame="83" m="0.989|0.148|-0.148|0.989"/>
      <data pos="16.25|-114.6" frame="84" m="0.989|0.148|-0.148|0.989"/>
      <data pos="16.25|-114.6" frame="85" m="0.989|0.148|-0.148|0.989"/>
      <data pos="16.25|-114.6" frame="86" m="0.989|0.148|-0.148|0.989"/>
      <data pos="16.25|-114.6" frame="87" m="0.989|0.148|-0.148|0.989"/>
      <data pos="16.25|-114.6" frame="88" m="0.989|0.148|-0.148|0.989"/>
    </LARGE_Leg_Back_Upper_01>
    <LARGE_Torso_01>
      <data pos="46.55|117.25" frame="1" m="0.998|-0.070|0.070|0.998"/>
      <data pos="1.9|129.4" frame="2" m="1.055|0.033|-0.111|1.013"/>
      <data pos="-35.9|139.6" frame="3" m="1.095|0.130|-0.265|1.000"/>
      <data pos="-66.8|148" frame="4" m="1.121|0.214|-0.393|0.971"/>
      <data pos="-90.8|154.5" frame="5" m="1.137|0.284|-0.490|0.937"/>
      <data pos="-107.9|159.15" frame="6" m="1.145|0.335|-0.558|0.907"/>
      <data pos="-118.25|162" frame="7" m="1.150|0.364|-0.596|0.888"/>
      <data pos="-121.65|162.9" frame="8" m="1.151|0.378|-0.611|0.881"/>
      <data pos="-121.65|162.9" frame="9" m="1.151|0.378|-0.611|0.881"/>
      <data pos="-121.65|162.9" frame="10" m="1.151|0.378|-0.611|0.881"/>
      <data pos="20.75|120.95" frame="11" m="1.196|-0.053|-0.071|1.072"/>
      <data pos="163.05|78.95" frame="12" m="1.085|-0.473|0.486|0.961"/>
      <data pos="166.95|77.95" frame="13" m="1.064|-0.464|0.503|0.944"/>
      <data pos="170.6|76.95" frame="14" m="1.045|-0.455|0.521|0.928"/>
      <data pos="174|76.05" frame="15" m="1.027|-0.448|0.535|0.914"/>
      <data pos="177.1|75.15" frame="16" m="1.010|-0.441|0.549|0.900"/>
      <data pos="180|74.35" frame="17" m="0.995|-0.434|0.562|0.887"/>
      <data pos="182.55|73.6" frame="18" m="0.981|-0.428|0.575|0.874"/>
      <data pos="185|72.95" frame="19" m="0.969|-0.423|0.584|0.864"/>
      <data pos="187.05|72.4" frame="20" m="0.958|-0.418|0.594|0.853"/>
      <data pos="188.95|71.85" frame="21" m="0.948|-0.414|0.600|0.846"/>
      <data pos="190.55|71.4" frame="22" m="0.939|-0.410|0.606|0.838"/>
      <data pos="192|71.15" frame="23" m="0.932|-0.407|0.612|0.831"/>
      <data pos="193.15|70.75" frame="24" m="0.926|-0.404|0.618|0.825"/>
      <data pos="193.95|70.45" frame="25" m="0.921|-0.402|0.621|0.821"/>
      <data pos="194.6|70.35" frame="26" m="0.918|-0.401|0.624|0.818"/>
      <data pos="195|70.25" frame="27" m="0.916|-0.400|0.624|0.817"/>
      <data pos="195.05|70.2" frame="28" m="0.916|-0.402|0.626|0.817"/>
      <data pos="195.05|70.2" frame="29" m="0.916|-0.402|0.626|0.817"/>
      <data pos="155.7|76.7" frame="30" m="0.934|-0.354|0.539|0.869"/>
      <data pos="116.35|83.25" frame="31" m="0.951|-0.305|0.446|0.913"/>
      <data pos="77|89.75" frame="32" m="0.966|-0.255|0.351|0.948"/>
      <data pos="37.7|96.25" frame="33" m="0.978|-0.205|0.253|0.973"/>
      <data pos="-1.7|102.8" frame="34" m="0.988|-0.157|0.157|0.988"/>
      <data pos="-1.7|102.8" frame="35" m="0.988|-0.157|0.157|0.988"/>
      <data pos="-1.7|102.8" frame="36" m="0.988|-0.157|0.157|0.988"/>
      <data pos="-1.7|102.8" frame="37" m="0.988|-0.157|0.157|0.988"/>
      <data pos="-1.7|102.8" frame="38" m="0.988|-0.157|0.157|0.988"/>
      <data pos="-1.7|102.8" frame="39" m="0.988|-0.157|0.157|0.988"/>
      <data pos="4.35|107.45" frame="40" m="0.992|-0.122|0.114|0.993"/>
      <data pos="10.4|112.15" frame="41" m="0.996|-0.088|0.074|0.997"/>
      <data pos="16.4|116.75" frame="42" m="0.998|-0.053|0.032|1.000"/>
      <data pos="22.5|121.5" frame="43" m="1.000|-0.022|-0.005|1.001"/>
      <data pos="28.55|126.25" frame="44" m="1.000|0.012|-0.048|1.000"/>
      <data pos="31.55|124.75" frame="45" m="1.000|-0.000|-0.027|1.000"/>
      <data pos="34.5|123.25" frame="46" m="1.000|-0.014|-0.005|1.000"/>
      <data pos="37.5|121.75" frame="47" m="1.000|-0.027|0.009|1.000"/>
      <data pos="40.55|120.2" frame="48" m="0.999|-0.040|0.031|1.000"/>
      <data pos="43.6|118.75" frame="49" m="0.998|-0.053|0.049|0.999"/>
      <data pos="46.55|117.25" frame="50" m="0.998|-0.070|0.070|0.998"/>
      <data pos="46.55|117.25" frame="51" m="0.998|-0.070|0.070|0.998"/>
      <data pos="46.55|117.25" frame="52" m="0.998|-0.070|0.070|0.998"/>
      <data pos="46.55|117.25" frame="53" m="0.998|-0.070|0.070|0.998"/>
      <data pos="46.55|117.25" frame="54" m="0.998|-0.070|0.070|0.998"/>
      <data pos="46.55|117.25" frame="55" m="0.998|-0.070|0.070|0.998"/>
      <data pos="46.55|117.25" frame="56" m="0.998|-0.070|0.070|0.998"/>
      <data pos="46.55|117.25" frame="57" m="0.998|-0.070|0.070|0.998"/>
      <data pos="46.55|117.25" frame="58" m="0.998|-0.070|0.070|0.998"/>
      <data pos="46.55|117.25" frame="59" m="0.998|-0.070|0.070|0.998"/>
      <data pos="46.55|117.25" frame="60" m="0.998|-0.070|0.070|0.998"/>
      <data pos="46.55|117.25" frame="61" m="0.998|-0.070|0.070|0.998"/>
      <data pos="46.55|117.25" frame="62" m="0.998|-0.070|0.070|0.998"/>
      <data pos="46.55|117.25" frame="63" m="0.998|-0.070|0.070|0.998"/>
      <data pos="46.55|117.25" frame="64" m="0.998|-0.070|0.070|0.998"/>
      <data pos="46.55|117.25" frame="65" m="0.998|-0.070|0.070|0.998"/>
      <data pos="46.55|117.25" frame="66" m="0.998|-0.070|0.070|0.998"/>
      <data pos="46.55|117.25" frame="67" m="0.998|-0.070|0.070|0.998"/>
      <data pos="46.55|117.25" frame="68" m="0.998|-0.070|0.070|0.998"/>
      <data pos="46.55|117.25" frame="69" m="0.998|-0.070|0.070|0.998"/>
      <data pos="46.55|117.25" frame="70" m="0.998|-0.070|0.070|0.998"/>
      <data pos="46.55|117.25" frame="71" m="0.998|-0.070|0.070|0.998"/>
      <data pos="46.55|117.25" frame="72" m="0.998|-0.070|0.070|0.998"/>
      <data pos="46.55|117.25" frame="73" m="0.998|-0.070|0.070|0.998"/>
      <data pos="46.55|117.25" frame="74" m="0.998|-0.070|0.070|0.998"/>
      <data pos="46.55|117.25" frame="75" m="0.998|-0.070|0.070|0.998"/>
      <data pos="46.55|117.25" frame="76" m="0.998|-0.070|0.070|0.998"/>
      <data pos="46.55|117.25" frame="77" m="0.998|-0.070|0.070|0.998"/>
      <data pos="46.55|117.25" frame="78" m="0.998|-0.070|0.070|0.998"/>
      <data pos="46.55|117.25" frame="79" m="0.998|-0.070|0.070|0.998"/>
      <data pos="46.55|117.25" frame="80" m="0.998|-0.070|0.070|0.998"/>
      <data pos="46.55|117.25" frame="81" m="0.998|-0.070|0.070|0.998"/>
      <data pos="46.55|117.25" frame="82" m="0.998|-0.070|0.070|0.998"/>
      <data pos="46.55|117.25" frame="83" m="0.998|-0.070|0.070|0.998"/>
      <data pos="46.55|117.25" frame="84" m="0.998|-0.070|0.070|0.998"/>
      <data pos="46.55|117.25" frame="85" m="0.998|-0.070|0.070|0.998"/>
      <data pos="46.55|117.25" frame="86" m="0.998|-0.070|0.070|0.998"/>
      <data pos="46.55|117.25" frame="87" m="0.998|-0.070|0.070|0.998"/>
      <data pos="46.55|117.25" frame="88" m="0.998|-0.070|0.070|0.998"/>
    </LARGE_Torso_01>
    <LARGE_Leg_Top_Lower_01>
      <data pos="-78.7|-208.15" frame="1" m="1.000|0.000|0.113|1.000"/>
      <data pos="-94.9|-209.15" frame="2" m="1.052|0.000|0.122|0.987"/>
      <data pos="-108.7|-209.9" frame="3" m="1.096|0.000|0.129|0.977"/>
      <data pos="-119.85|-210.65" frame="4" m="1.132|0.000|0.137|0.968"/>
      <data pos="-128.65|-211.15" frame="5" m="1.161|0.000|0.140|0.962"/>
      <data pos="-134.9|-211.55" frame="6" m="1.181|0.000|0.144|0.957"/>
      <data pos="-138.65|-211.75" frame="7" m="1.193|0.000|0.147|0.954"/>
      <data pos="-139.9|-211.85" frame="8" m="1.197|0.000|0.149|0.953"/>
      <data pos="-139.9|-211.85" frame="9" m="1.197|0.000|0.149|0.953"/>
      <data pos="-139.9|-211.85" frame="10" m="1.197|0.000|0.149|0.953"/>
      <data pos="-125.65|-217.4" frame="11" m="1.269|0.000|0.185|0.924"/>
      <data pos="-111.4|-222.9" frame="12" m="1.341|0.000|0.222|0.895"/>
      <data pos="-108.9|-222.85" frame="13" m="1.344|0.000|0.236|0.895"/>
      <data pos="-106.6|-222.9" frame="14" m="1.347|0.000|0.249|0.896"/>
      <data pos="-104.4|-222.9" frame="15" m="1.350|0.000|0.262|0.897"/>
      <data pos="-102.4|-222.9" frame="16" m="1.353|0.000|0.275|0.897"/>
      <data pos="-100.6|-222.9" frame="17" m="1.355|0.000|0.288|0.896"/>
      <data pos="-98.85|-222.9" frame="18" m="1.358|0.000|0.297|0.897"/>
      <data pos="-97.25|-222.9" frame="19" m="1.360|0.000|0.306|0.897"/>
      <data pos="-95.85|-222.85" frame="20" m="1.362|0.000|0.314|0.896"/>
      <data pos="-94.7|-222.9" frame="21" m="1.363|0.000|0.323|0.896"/>
      <data pos="-93.65|-222.9" frame="22" m="1.365|0.000|0.331|0.895"/>
      <data pos="-92.75|-222.9" frame="23" m="1.366|0.000|0.335|0.895"/>
      <data pos="-92|-222.9" frame="24" m="1.367|0.000|0.340|0.895"/>
      <data pos="-91.45|-222.85" frame="25" m="1.368|0.000|0.344|0.894"/>
      <data pos="-91.05|-222.9" frame="26" m="1.368|0.000|0.345|0.895"/>
      <data pos="-90.85|-222.9" frame="27" m="1.369|0.000|0.348|0.894"/>
      <data pos="-90.7|-222.9" frame="28" m="1.369|0.000|0.349|0.895"/>
      <data pos="-90.7|-222.9" frame="29" m="1.369|0.000|0.349|0.895"/>
      <data pos="-105.5|-220.4" frame="30" m="1.295|0.000|0.317|0.918"/>
      <data pos="-120.5|-217.9" frame="31" m="1.221|0.000|0.284|0.940"/>
      <data pos="-135.3|-215.4" frame="32" m="1.147|0.000|0.250|0.961"/>
      <data pos="-150.2|-212.9" frame="33" m="1.074|0.000|0.214|0.981"/>
      <data pos="-165.05|-208.15" frame="34" m="1.000|0.000|0.182|1.000"/>
      <data pos="-165.05|-208.15" frame="35" m="1.000|0.000|0.182|1.000"/>
      <data pos="-165.05|-208.15" frame="36" m="1.000|0.000|0.182|1.000"/>
      <data pos="-165.05|-208.15" frame="37" m="1.000|0.000|0.182|1.000"/>
      <data pos="-165.05|-208.15" frame="38" m="1.000|0.000|0.182|1.000"/>
      <data pos="-165.05|-208.15" frame="39" m="1.000|0.000|0.182|1.000"/>
      <data pos="-146.9|-207.7" frame="40" m="1.000|0.000|0.172|1.000"/>
      <data pos="-128.8|-207.2" frame="41" m="1.000|0.000|0.160|1.000"/>
      <data pos="-110.6|-206.85" frame="42" m="1.000|0.000|0.151|1.000"/>
      <data pos="-92.45|-206.4" frame="43" m="1.000|0.000|0.142|1.000"/>
      <data pos="-74.25|-208.15" frame="44" m="1.000|0.000|0.135|1.000"/>
      <data pos="-75.05|-208.15" frame="45" m="1.000|0.000|0.128|1.000"/>
      <data pos="-75.8|-208.15" frame="46" m="1.000|0.000|0.127|1.000"/>
      <data pos="-76.45|-208.15" frame="47" m="1.000|0.000|0.123|1.000"/>
      <data pos="-77.25|-208.15" frame="48" m="1.000|0.000|0.119|1.000"/>
      <data pos="-77.95|-208.15" frame="49" m="1.000|0.000|0.115|1.000"/>
      <data pos="-78.7|-208.15" frame="50" m="1.000|0.000|0.113|1.000"/>
      <data pos="-78.7|-208.15" frame="51" m="1.000|0.000|0.113|1.000"/>
      <data pos="-78.7|-208.15" frame="52" m="1.000|0.000|0.113|1.000"/>
      <data pos="-78.7|-208.15" frame="53" m="1.000|0.000|0.113|1.000"/>
      <data pos="-78.7|-208.15" frame="54" m="1.000|0.000|0.113|1.000"/>
      <data pos="-78.7|-208.15" frame="55" m="1.000|0.000|0.113|1.000"/>
      <data pos="-78.7|-208.15" frame="56" m="1.000|0.000|0.113|1.000"/>
      <data pos="-78.7|-208.15" frame="57" m="1.000|0.000|0.113|1.000"/>
      <data pos="-78.7|-208.15" frame="58" m="1.000|0.000|0.113|1.000"/>
      <data pos="-78.7|-208.15" frame="59" m="1.000|0.000|0.113|1.000"/>
      <data pos="-78.7|-208.15" frame="60" m="1.000|0.000|0.113|1.000"/>
      <data pos="-78.7|-208.15" frame="61" m="1.000|0.000|0.113|1.000"/>
      <data pos="-78.7|-208.15" frame="62" m="1.000|0.000|0.113|1.000"/>
      <data pos="-78.7|-208.15" frame="63" m="1.000|0.000|0.113|1.000"/>
      <data pos="-78.7|-208.15" frame="64" m="1.000|0.000|0.113|1.000"/>
      <data pos="-78.7|-208.15" frame="65" m="1.000|0.000|0.113|1.000"/>
      <data pos="-78.7|-208.15" frame="66" m="1.000|0.000|0.113|1.000"/>
      <data pos="-78.7|-208.15" frame="67" m="1.000|0.000|0.113|1.000"/>
      <data pos="-78.7|-208.15" frame="68" m="1.000|0.000|0.113|1.000"/>
      <data pos="-78.7|-208.15" frame="69" m="1.000|0.000|0.113|1.000"/>
      <data pos="-78.7|-208.15" frame="70" m="1.000|0.000|0.113|1.000"/>
      <data pos="-78.7|-208.15" frame="71" m="1.000|0.000|0.113|1.000"/>
      <data pos="-78.7|-208.15" frame="72" m="1.000|0.000|0.113|1.000"/>
      <data pos="-78.7|-208.15" frame="73" m="1.000|0.000|0.113|1.000"/>
      <data pos="-78.7|-208.15" frame="74" m="1.000|0.000|0.113|1.000"/>
      <data pos="-78.7|-208.15" frame="75" m="1.000|0.000|0.113|1.000"/>
      <data pos="-78.7|-208.15" frame="76" m="1.000|0.000|0.113|1.000"/>
      <data pos="-78.7|-208.15" frame="77" m="1.000|0.000|0.113|1.000"/>
      <data pos="-78.7|-208.15" frame="78" m="1.000|0.000|0.113|1.000"/>
      <data pos="-78.7|-208.15" frame="79" m="1.000|0.000|0.113|1.000"/>
      <data pos="-78.7|-208.15" frame="80" m="1.000|0.000|0.113|1.000"/>
      <data pos="-78.7|-208.15" frame="81" m="1.000|0.000|0.113|1.000"/>
      <data pos="-78.7|-208.15" frame="82" m="1.000|0.000|0.113|1.000"/>
      <data pos="-78.7|-208.15" frame="83" m="1.000|0.000|0.113|1.000"/>
      <data pos="-78.7|-208.15" frame="84" m="1.000|0.000|0.113|1.000"/>
      <data pos="-78.7|-208.15" frame="85" m="1.000|0.000|0.113|1.000"/>
      <data pos="-78.7|-208.15" frame="86" m="1.000|0.000|0.113|1.000"/>
      <data pos="-78.7|-208.15" frame="87" m="1.000|0.000|0.113|1.000"/>
      <data pos="-78.7|-208.15" frame="88" m="1.000|0.000|0.113|1.000"/>
    </LARGE_Leg_Top_Lower_01>
    <LARGE_Leg_Top_Upper_01>
      <data pos="-76.6|-134.25" frame="1" m="1.000|0.000|-0.109|1.000"/>
      <data pos="-94.35|-133.45" frame="2" m="0.998|0.014|-0.097|1.093"/>
      <data pos="-109.25|-132.85" frame="3" m="0.996|0.031|-0.088|1.172"/>
      <data pos="-121.45|-132.25" frame="4" m="0.994|0.044|-0.077|1.237"/>
      <data pos="-131|-131.85" frame="5" m="0.992|0.052|-0.068|1.287"/>
      <data pos="-137.85|-131.6" frame="6" m="0.991|0.057|-0.064|1.323"/>
      <data pos="-141.9|-131.35" frame="7" m="0.990|0.061|-0.059|1.345"/>
      <data pos="-143.25|-131.3" frame="8" m="0.990|0.065|-0.058|1.352"/>
      <data pos="-143.25|-131.3" frame="9" m="0.990|0.065|-0.058|1.352"/>
      <data pos="-143.25|-131.3" frame="10" m="0.990|0.065|-0.058|1.352"/>
      <data pos="-111.05|-131.85" frame="11" m="1.070|-0.038|0.107|1.270"/>
      <data pos="-79.1|-132.35" frame="12" m="1.137|-0.165|0.255|1.170"/>
      <data pos="-75.65|-131.85" frame="13" m="1.144|-0.156|0.254|1.169"/>
      <data pos="-72.25|-131.3" frame="14" m="1.151|-0.147|0.255|1.169"/>
      <data pos="-69.25|-130.75" frame="15" m="1.157|-0.142|0.255|1.169"/>
      <data pos="-66.45|-130.3" frame="16" m="1.164|-0.134|0.255|1.169"/>
      <data pos="-63.8|-129.85" frame="17" m="1.169|-0.129|0.255|1.169"/>
      <data pos="-61.45|-129.55" frame="18" m="1.174|-0.124|0.255|1.169"/>
      <data pos="-59.3|-129.25" frame="19" m="1.178|-0.119|0.255|1.169"/>
      <data pos="-57.4|-128.9" frame="20" m="1.182|-0.114|0.259|1.168"/>
      <data pos="-55.7|-128.6" frame="21" m="1.186|-0.110|0.259|1.168"/>
      <data pos="-54.2|-128.35" frame="22" m="1.189|-0.105|0.259|1.168"/>
      <data pos="-53|-128.1" frame="23" m="1.191|-0.104|0.259|1.168"/>
      <data pos="-51.95|-128" frame="24" m="1.194|-0.100|0.259|1.168"/>
      <data pos="-51.15|-127.85" frame="25" m="1.195|-0.100|0.259|1.168"/>
      <data pos="-50.6|-127.75" frame="26" m="1.196|-0.095|0.259|1.168"/>
      <data pos="-50.3|-127.75" frame="27" m="1.197|-0.095|0.259|1.168"/>
      <data pos="-50.15|-127.65" frame="28" m="1.197|-0.098|0.261|1.169"/>
      <data pos="-50.15|-127.65" frame="29" m="1.197|-0.098|0.261|1.169"/>
      <data pos="-71.05|-131.2" frame="30" m="1.155|-0.117|0.217|1.138"/>
      <data pos="-91.9|-134.7" frame="31" m="1.112|-0.137|0.181|1.105"/>
      <data pos="-112.9|-138.15" frame="32" m="1.069|-0.155|0.142|1.073"/>
      <data pos="-133.8|-141.65" frame="33" m="1.025|-0.172|0.110|1.038"/>
      <data pos="-154.7|-145.15" frame="34" m="0.982|-0.186|0.079|1.003"/>
      <data pos="-154.7|-145.15" frame="35" m="0.982|-0.186|0.079|1.003"/>
      <data pos="-154.7|-145.15" frame="36" m="0.982|-0.186|0.079|1.003"/>
      <data pos="-154.7|-145.15" frame="37" m="0.982|-0.186|0.079|1.003"/>
      <data pos="-154.7|-145.15" frame="38" m="0.982|-0.186|0.079|1.003"/>
      <data pos="-154.7|-145.15" frame="39" m="0.982|-0.186|0.079|1.003"/>
      <data pos="-136.35|-141.15" frame="40" m="0.988|-0.153|0.048|1.005"/>
      <data pos="-118|-137.25" frame="41" m="0.992|-0.123|0.018|1.006"/>
      <data pos="-99.7|-133.2" frame="42" m="0.995|-0.093|-0.010|1.006"/>
      <data pos="-81.4|-129.25" frame="43" m="0.998|-0.062|-0.040|1.005"/>
      <data pos="-63.1|-125.25" frame="44" m="0.999|-0.035|-0.074|1.003"/>
      <data pos="-65.35|-126.75" frame="45" m="1.000|-0.027|-0.079|1.003"/>
      <data pos="-67.6|-128.25" frame="46" m="1.000|-0.022|-0.084|1.002"/>
      <data pos="-69.85|-129.75" frame="47" m="1.000|-0.014|-0.089|1.002"/>
      <data pos="-72.1|-131.25" frame="48" m="1.000|-0.009|-0.097|1.001"/>
      <data pos="-74.35|-132.75" frame="49" m="1.000|-0.005|-0.101|1.000"/>
      <data pos="-76.6|-134.25" frame="50" m="1.000|0.000|-0.109|1.000"/>
      <data pos="-76.6|-134.25" frame="51" m="1.000|0.000|-0.109|1.000"/>
      <data pos="-76.6|-134.25" frame="52" m="1.000|0.000|-0.109|1.000"/>
      <data pos="-76.6|-134.25" frame="53" m="1.000|0.000|-0.109|1.000"/>
      <data pos="-76.6|-134.25" frame="54" m="1.000|0.000|-0.109|1.000"/>
      <data pos="-76.6|-134.25" frame="55" m="1.000|0.000|-0.109|1.000"/>
      <data pos="-76.6|-134.25" frame="56" m="1.000|0.000|-0.109|1.000"/>
      <data pos="-76.6|-134.25" frame="57" m="1.000|0.000|-0.109|1.000"/>
      <data pos="-76.6|-134.25" frame="58" m="1.000|0.000|-0.109|1.000"/>
      <data pos="-76.6|-134.25" frame="59" m="1.000|0.000|-0.109|1.000"/>
      <data pos="-76.6|-134.25" frame="60" m="1.000|0.000|-0.109|1.000"/>
      <data pos="-76.6|-134.25" frame="61" m="1.000|0.000|-0.109|1.000"/>
      <data pos="-76.6|-134.25" frame="62" m="1.000|0.000|-0.109|1.000"/>
      <data pos="-76.6|-134.25" frame="63" m="1.000|0.000|-0.109|1.000"/>
      <data pos="-76.6|-134.25" frame="64" m="1.000|0.000|-0.109|1.000"/>
      <data pos="-76.6|-134.25" frame="65" m="1.000|0.000|-0.109|1.000"/>
      <data pos="-76.6|-134.25" frame="66" m="1.000|0.000|-0.109|1.000"/>
      <data pos="-76.6|-134.25" frame="67" m="1.000|0.000|-0.109|1.000"/>
      <data pos="-76.6|-134.25" frame="68" m="1.000|0.000|-0.109|1.000"/>
      <data pos="-76.6|-134.25" frame="69" m="1.000|0.000|-0.109|1.000"/>
      <data pos="-76.6|-134.25" frame="70" m="1.000|0.000|-0.109|1.000"/>
      <data pos="-76.6|-134.25" frame="71" m="1.000|0.000|-0.109|1.000"/>
      <data pos="-76.6|-134.25" frame="72" m="1.000|0.000|-0.109|1.000"/>
      <data pos="-76.6|-134.25" frame="73" m="1.000|0.000|-0.109|1.000"/>
      <data pos="-76.6|-134.25" frame="74" m="1.000|0.000|-0.109|1.000"/>
      <data pos="-76.6|-134.25" frame="75" m="1.000|0.000|-0.109|1.000"/>
      <data pos="-76.6|-134.25" frame="76" m="1.000|0.000|-0.109|1.000"/>
      <data pos="-76.6|-134.25" frame="77" m="1.000|0.000|-0.109|1.000"/>
      <data pos="-76.6|-134.25" frame="78" m="1.000|0.000|-0.109|1.000"/>
      <data pos="-76.6|-134.25" frame="79" m="1.000|0.000|-0.109|1.000"/>
      <data pos="-76.6|-134.25" frame="80" m="1.000|0.000|-0.109|1.000"/>
      <data pos="-76.6|-134.25" frame="81" m="1.000|0.000|-0.109|1.000"/>
      <data pos="-76.6|-134.25" frame="82" m="1.000|0.000|-0.109|1.000"/>
      <data pos="-76.6|-134.25" frame="83" m="1.000|0.000|-0.109|1.000"/>
      <data pos="-76.6|-134.25" frame="84" m="1.000|0.000|-0.109|1.000"/>
      <data pos="-76.6|-134.25" frame="85" m="1.000|0.000|-0.109|1.000"/>
      <data pos="-76.6|-134.25" frame="86" m="1.000|0.000|-0.109|1.000"/>
      <data pos="-76.6|-134.25" frame="87" m="1.000|0.000|-0.109|1.000"/>
      <data pos="-76.6|-134.25" frame="88" m="1.000|0.000|-0.109|1.000"/>
    </LARGE_Leg_Top_Upper_01>
    <LARGE_Arm_Top_Upper_01>
      <data pos="-107.45|120.3" frame="1" m="0.967|-0.254|0.254|0.967"/>
      <data pos="-149.6|131.05" frame="2" m="0.910|-0.411|0.401|0.889"/>
      <data pos="-185.25|140.1" frame="3" m="0.844|-0.534|0.510|0.807"/>
      <data pos="-214.45|147.65" frame="4" m="0.777|-0.627|0.589|0.730"/>
      <data pos="-237.15|153.35" frame="5" m="0.717|-0.695|0.644|0.664"/>
      <data pos="-253.4|157.5" frame="6" m="0.670|-0.740|0.679|0.615"/>
      <data pos="-263.1|159.9" frame="7" m="0.643|-0.764|0.697|0.586"/>
      <data pos="-266.3|160.75" frame="8" m="0.633|-0.774|0.704|0.577"/>
      <data pos="-266.3|160.75" frame="9" m="0.633|-0.774|0.704|0.577"/>
      <data pos="-266.3|160.75" frame="10" m="0.633|-0.774|0.704|0.577"/>
      <data pos="-138.2|146" frame="11" m="0.995|-0.099|0.094|0.950"/>
      <data pos="59|113.3" frame="12" m="0.365|0.931|-0.931|0.365"/>
      <data pos="67.75|109.15" frame="13" m="0.305|0.951|-0.951|0.305"/>
      <data pos="76.05|105.3" frame="14" m="0.251|0.967|-0.967|0.251"/>
      <data pos="83.75|101.75" frame="15" m="0.199|0.979|-0.979|0.199"/>
      <data pos="90.8|98.4" frame="16" m="0.149|0.988|-0.988|0.149"/>
      <data pos="97.4|95.4" frame="17" m="0.105|0.994|-0.994|0.105"/>
      <data pos="103.35|92.55" frame="18" m="0.062|0.998|-0.998|0.062"/>
      <data pos="108.65|90.05" frame="19" m="0.026|0.999|-0.999|0.026"/>
      <data pos="113.55|87.8" frame="20" m="-0.005|1.000|-1.000|-0.005"/>
      <data pos="117.8|85.8" frame="21" m="-0.035|0.999|-0.999|-0.035"/>
      <data pos="121.55|84" frame="22" m="-0.061|0.998|-0.998|-0.061"/>
      <data pos="124.65|82.6" frame="23" m="-0.083|0.996|-0.996|-0.083"/>
      <data pos="127.2|81.45" frame="24" m="-0.101|0.995|-0.995|-0.101"/>
      <data pos="129.2|80.5" frame="25" m="-0.114|0.993|-0.993|-0.114"/>
      <data pos="130.6|79.85" frame="26" m="-0.123|0.992|-0.992|-0.123"/>
      <data pos="131.4|79.45" frame="27" m="-0.131|0.991|-0.991|-0.131"/>
      <data pos="131.8|79.35" frame="28" m="-0.133|0.991|-0.991|-0.133"/>
      <data pos="131.8|79.35" frame="29" m="-0.133|0.991|-0.991|-0.133"/>
      <data pos="74.95|91.2" frame="30" m="0.326|0.944|-0.944|0.326"/>
      <data pos="18.25|103.1" frame="31" m="0.717|0.695|-0.695|0.717"/>
      <data pos="-38.6|114.85" frame="32" m="0.954|0.297|-0.297|0.954"/>
      <data pos="-95.3|126.75" frame="33" m="0.986|-0.165|0.165|0.986"/>
      <data pos="-152.1|138.55" frame="34" m="0.805|-0.593|0.593|0.805"/>
      <data pos="-152.1|138.55" frame="35" m="0.805|-0.593|0.593|0.805"/>
      <data pos="-152.1|138.55" frame="36" m="0.805|-0.593|0.593|0.805"/>
      <data pos="-152.1|138.55" frame="37" m="0.805|-0.593|0.593|0.805"/>
      <data pos="-152.1|138.55" frame="38" m="0.805|-0.593|0.593|0.805"/>
      <data pos="-152.1|138.55" frame="39" m="0.805|-0.593|0.593|0.805"/>
      <data pos="-143.65|135.6" frame="40" m="0.860|-0.508|0.508|0.860"/>
      <data pos="-135.15|132.65" frame="41" m="0.908|-0.416|0.416|0.908"/>
      <data pos="-126.7|129.7" frame="42" m="0.946|-0.322|0.322|0.946"/>
      <data pos="-118.25|126.85" frame="43" m="0.974|-0.225|0.225|0.974"/>
      <data pos="-109.75|123.9" frame="44" m="0.992|-0.127|0.127|0.992"/>
      <data pos="-109.35|123.3" frame="45" m="0.989|-0.148|0.148|0.989"/>
      <data pos="-109|122.75" frame="46" m="0.985|-0.169|0.169|0.985"/>
      <data pos="-108.6|122.1" frame="47" m="0.981|-0.191|0.191|0.981"/>
      <data pos="-108.25|121.55" frame="48" m="0.977|-0.209|0.209|0.977"/>
      <data pos="-107.9|120.9" frame="49" m="0.972|-0.230|0.230|0.972"/>
      <data pos="-107.45|120.3" frame="50" m="0.967|-0.254|0.254|0.967"/>
      <data pos="-107.45|120.3" frame="51" m="0.967|-0.254|0.254|0.967"/>
      <data pos="-107.45|120.3" frame="52" m="0.967|-0.254|0.254|0.967"/>
      <data pos="-107.45|120.3" frame="53" m="0.967|-0.254|0.254|0.967"/>
      <data pos="-107.45|120.3" frame="54" m="0.967|-0.254|0.254|0.967"/>
      <data pos="-107.45|120.3" frame="55" m="0.967|-0.254|0.254|0.967"/>
      <data pos="-107.45|120.3" frame="56" m="0.967|-0.254|0.254|0.967"/>
      <data pos="-107.45|120.3" frame="57" m="0.967|-0.254|0.254|0.967"/>
      <data pos="-107.45|120.3" frame="58" m="0.967|-0.254|0.254|0.967"/>
      <data pos="-107.45|120.3" frame="59" m="0.967|-0.254|0.254|0.967"/>
      <data pos="-107.45|120.3" frame="60" m="0.967|-0.254|0.254|0.967"/>
      <data pos="-107.45|120.3" frame="61" m="0.967|-0.254|0.254|0.967"/>
      <data pos="-107.45|120.3" frame="62" m="0.967|-0.254|0.254|0.967"/>
      <data pos="-107.45|120.3" frame="63" m="0.967|-0.254|0.254|0.967"/>
      <data pos="-107.45|120.3" frame="64" m="0.967|-0.254|0.254|0.967"/>
      <data pos="-107.45|120.3" frame="65" m="0.967|-0.254|0.254|0.967"/>
      <data pos="-107.45|120.3" frame="66" m="0.967|-0.254|0.254|0.967"/>
      <data pos="-107.45|120.3" frame="67" m="0.967|-0.254|0.254|0.967"/>
      <data pos="-107.45|120.3" frame="68" m="0.967|-0.254|0.254|0.967"/>
      <data pos="-107.45|120.3" frame="69" m="0.967|-0.254|0.254|0.967"/>
      <data pos="-107.45|120.3" frame="70" m="0.967|-0.254|0.254|0.967"/>
      <data pos="-107.45|120.3" frame="71" m="0.967|-0.254|0.254|0.967"/>
      <data pos="-107.45|120.3" frame="72" m="0.967|-0.254|0.254|0.967"/>
      <data pos="-107.45|120.3" frame="73" m="0.967|-0.254|0.254|0.967"/>
      <data pos="-107.45|120.3" frame="74" m="0.967|-0.254|0.254|0.967"/>
      <data pos="-107.45|120.3" frame="75" m="0.967|-0.254|0.254|0.967"/>
      <data pos="-107.45|120.3" frame="76" m="0.967|-0.254|0.254|0.967"/>
      <data pos="-107.45|120.3" frame="77" m="0.967|-0.254|0.254|0.967"/>
      <data pos="-107.45|120.3" frame="78" m="0.967|-0.254|0.254|0.967"/>
      <data pos="-107.45|120.3" frame="79" m="0.967|-0.254|0.254|0.967"/>
      <data pos="-107.45|120.3" frame="80" m="0.967|-0.254|0.254|0.967"/>
      <data pos="-107.45|120.3" frame="81" m="0.967|-0.254|0.254|0.967"/>
      <data pos="-107.45|120.3" frame="82" m="0.967|-0.254|0.254|0.967"/>
      <data pos="-107.45|120.3" frame="83" m="0.967|-0.254|0.254|0.967"/>
      <data pos="-107.45|120.3" frame="84" m="0.967|-0.254|0.254|0.967"/>
      <data pos="-107.45|120.3" frame="85" m="0.967|-0.254|0.254|0.967"/>
      <data pos="-107.45|120.3" frame="86" m="0.967|-0.254|0.254|0.967"/>
      <data pos="-107.45|120.3" frame="87" m="0.967|-0.254|0.254|0.967"/>
      <data pos="-107.45|120.3" frame="88" m="0.967|-0.254|0.254|0.967"/>
    </LARGE_Arm_Top_Upper_01>
    <LARGE_Head_01>
      <data pos="30.3|164" frame="1" m="1.000|0.000|0.000|1.000"/>
      <data pos="-98.3|189.65" frame="2" m="0.984|0.246|-0.246|0.984"/>
      <data pos="-175.55|205.05" frame="3" m="0.944|0.393|-0.393|0.944"/>
      <data pos="-201.2|210.2" frame="4" m="0.926|0.443|-0.443|0.926"/>
      <data pos="-216.65|213.3" frame="5" m="0.001|0|0|0.001" v="0"/>
      <data pos="-16.15|114.9" frame="34" m="0.991|-0.131|0.131|0.991"/>
      <data pos="-16.15|114.9" frame="35" m="0.991|-0.131|0.131|0.991"/>
      <data pos="-16.15|114.9" frame="36" m="0.991|-0.131|0.131|0.991"/>
      <data pos="-16.15|114.9" frame="37" m="0.991|-0.131|0.131|0.991"/>
      <data pos="-16.15|114.9" frame="38" m="0.991|-0.131|0.131|0.991"/>
      <data pos="-16.15|114.9" frame="39" m="0.991|-0.131|0.131|0.991"/>
      <data pos="-11.4|128.3" frame="40" m="0.995|-0.092|0.092|0.995"/>
      <data pos="-6.55|141.8" frame="41" m="0.998|-0.053|0.053|0.998"/>
      <data pos="-1.85|155.1" frame="42" m="1.000|-0.014|0.014|1.000"/>
      <data pos="3|168.65" frame="43" m="1.000|0.022|-0.022|1.000"/>
      <data pos="7.8|182" frame="44" m="0.998|0.060|-0.060|0.998"/>
      <data pos="11.6|179" frame="45" m="0.999|0.049|-0.049|0.999"/>
      <data pos="15.3|176" frame="46" m="0.999|0.039|-0.039|0.999"/>
      <data pos="19|173.05" frame="47" m="1.000|0.027|-0.027|1.000"/>
      <data pos="22.8|170" frame="48" m="1.000|0.018|-0.018|1.000"/>
      <data pos="26.55|167" frame="49" m="1.000|0.009|-0.009|1.000"/>
      <data pos="30.3|164" frame="50" m="1.000|0.000|0.000|1.000"/>
      <data pos="30.3|164" frame="51" m="1.000|0.000|0.000|1.000"/>
      <data pos="30.3|164" frame="52" m="1.000|0.000|0.000|1.000"/>
      <data pos="30.3|164" frame="53" m="1.000|0.000|0.000|1.000"/>
      <data pos="30.3|164" frame="54" m="1.000|0.000|0.000|1.000"/>
      <data pos="30.3|164" frame="55" m="1.000|0.000|0.000|1.000"/>
      <data pos="30.3|164" frame="56" m="1.000|0.000|0.000|1.000"/>
      <data pos="30.3|164" frame="57" m="1.000|0.000|0.000|1.000"/>
      <data pos="30.3|164" frame="58" m="1.000|0.000|0.000|1.000"/>
      <data pos="30.3|164" frame="59" m="1.000|0.000|0.000|1.000"/>
      <data pos="30.3|164" frame="60" m="1.000|0.000|0.000|1.000"/>
      <data pos="30.3|164" frame="61" m="1.000|0.000|0.000|1.000"/>
      <data pos="30.3|164" frame="62" m="1.000|0.000|0.000|1.000"/>
      <data pos="30.3|164" frame="63" m="1.000|0.000|0.000|1.000"/>
      <data pos="30.3|164" frame="64" m="1.000|0.000|0.000|1.000"/>
      <data pos="30.3|164" frame="65" m="1.000|0.000|0.000|1.000"/>
      <data pos="30.3|164" frame="66" m="1.000|0.000|0.000|1.000"/>
      <data pos="30.3|164" frame="67" m="1.000|0.000|0.000|1.000"/>
      <data pos="30.3|164" frame="68" m="1.000|0.000|0.000|1.000"/>
      <data pos="30.3|164" frame="69" m="1.000|0.000|0.000|1.000"/>
      <data pos="30.3|164" frame="70" m="1.000|0.000|0.000|1.000"/>
      <data pos="30.3|164" frame="71" m="1.000|0.000|0.000|1.000"/>
      <data pos="30.3|164" frame="72" m="1.000|0.000|0.000|1.000"/>
      <data pos="30.3|164" frame="73" m="1.000|0.000|0.000|1.000"/>
      <data pos="30.3|164" frame="74" m="1.000|0.000|0.000|1.000"/>
      <data pos="30.3|164" frame="75" m="1.000|0.000|0.000|1.000"/>
      <data pos="30.3|164" frame="76" m="1.000|0.000|0.000|1.000"/>
      <data pos="30.3|164" frame="77" m="1.000|0.000|0.000|1.000"/>
      <data pos="30.3|164" frame="78" m="1.000|0.000|0.000|1.000"/>
      <data pos="30.3|164" frame="79" m="1.000|0.000|0.000|1.000"/>
      <data pos="30.3|164" frame="80" m="1.000|0.000|0.000|1.000"/>
      <data pos="30.3|164" frame="81" m="1.000|0.000|0.000|1.000"/>
      <data pos="30.3|164" frame="82" m="1.000|0.000|0.000|1.000"/>
      <data pos="30.3|164" frame="83" m="1.000|0.000|0.000|1.000"/>
      <data pos="30.3|164" frame="84" m="1.000|0.000|0.000|1.000"/>
      <data pos="30.3|164" frame="85" m="1.000|0.000|0.000|1.000"/>
      <data pos="30.3|164" frame="86" m="1.000|0.000|0.000|1.000"/>
      <data pos="30.3|164" frame="87" m="1.000|0.000|0.000|1.000"/>
      <data pos="30.3|164" frame="88" m="1.000|0.000|0.000|1.000"/>
    </LARGE_Head_01>
    <LARGE_Head_04>
      <data pos="30.3|164" frame="1" m="0.001|0|0|0.001" v="0"/>
      <data pos="-216.65|213.3" frame="5" m="0.915|0.473|-0.473|0.915"/>
      <data pos="-235.15|217.05" frame="6" m="0.899|0.506|-0.506|0.899"/>
      <data pos="-253.7|220.75" frame="7" m="0.881|0.541|-0.541|0.881"/>
      <data pos="-272.25|224.4" frame="8" m="0.865|0.575|-0.575|0.865"/>
      <data pos="-272.25|224.4" frame="9" m="0.865|0.575|-0.575|0.865"/>
      <data pos="-272.25|224.4" frame="10" m="0.865|0.575|-0.575|0.865"/>
      <data pos="-58.25|172.65" frame="11" m="0.984|0.340|-0.340|0.984"/>
      <data pos="-58.25|172.65" frame="12" m="0.001|0|0|0.001" v="0"/>
    </LARGE_Head_04>
    <LARGE_Head_14>
      <data pos="155.75|120.95" frame="1" m="0.001|0|0|0.001" v="0"/>
      <data pos="155.75|120.95" frame="12" m="1.042|0.084|-0.084|1.042"/>
      <data pos="166.65|118.6" frame="13" m="1.034|0.109|-0.109|1.034"/>
      <data pos="176.85|116.3" frame="14" m="1.026|0.132|-0.132|1.026"/>
      <data pos="186.4|114.25" frame="15" m="1.018|0.157|-0.157|1.018"/>
      <data pos="195.15|112.3" frame="16" m="1.009|0.178|-0.178|1.009"/>
      <data pos="203.25|110.45" frame="17" m="1.002|0.196|-0.196|1.002"/>
      <data pos="210.7|108.85" frame="18" m="0.995|0.212|-0.212|0.995"/>
      <data pos="217.45|107.35" frame="19" m="0.988|0.229|-0.229|0.988"/>
      <data pos="223.35|106.05" frame="20" m="0.981|0.241|-0.241|0.981"/>
      <data pos="228.6|104.9" frame="21" m="0.976|0.253|-0.253|0.976"/>
      <data pos="233.2|103.95" frame="22" m="0.970|0.265|-0.265|0.970"/>
      <data pos="237.05|103.1" frame="23" m="0.966|0.273|-0.273|0.966"/>
      <data pos="240.2|102.4" frame="24" m="0.963|0.277|-0.277|0.963"/>
      <data pos="242.75|101.85" frame="25" m="0.959|0.285|-0.285|0.959"/>
      <data pos="244.45|101.45" frame="26" m="0.957|0.289|-0.289|0.957"/>
      <data pos="245.5|101.25" frame="27" m="0.957|0.289|-0.289|0.957"/>
      <data pos="245.9|101.15" frame="28" m="0.956|0.293|-0.293|0.956"/>
      <data pos="245.9|101.15" frame="29" m="0.956|0.293|-0.293|0.956"/>
      <data pos="193.45|103.85" frame="30" m="0.977|0.208|-0.208|0.977"/>
      <data pos="141.05|106.65" frame="31" m="0.992|0.123|-0.123|0.992"/>
      <data pos="88.65|109.45" frame="32" m="0.999|0.040|-0.040|0.999"/>
      <data pos="36.25|112.2" frame="33" m="0.999|-0.044|0.044|0.999"/>
      <data pos="36.25|112.2" frame="34" m="0.001|0|0|0.001" v="0"/>
    </LARGE_Head_14>
    <LARGE_Arm_Top_Lower_01>
      <data pos="-266.45|16.9" frame="1" m="0.967|-0.254|0.254|0.967"/>
      <data pos="-323.85|65.4" frame="2" m="0.447|-0.892|0.892|0.447"/>
      <data pos="-380.55|94.1" frame="3" m="0.183|-0.982|0.982|0.183"/>
      <data pos="-394.8|135.5" frame="4" m="0.044|-0.999|0.999|0.044"/>
      <data pos="-394.8|135.5" frame="5" m="0.001|0|0|0.001" v="0"/>
      <data pos="-342.4|105.7" frame="34" m="0.514|-0.858|0.858|0.514"/>
      <data pos="-342.4|105.7" frame="35" m="0.514|-0.858|0.858|0.514"/>
      <data pos="-342.4|105.7" frame="36" m="0.514|-0.858|0.858|0.514"/>
      <data pos="-342.4|105.7" frame="37" m="0.514|-0.858|0.858|0.514"/>
      <data pos="-342.4|105.7" frame="38" m="0.514|-0.858|0.858|0.514"/>
      <data pos="-342.4|105.7" frame="39" m="0.514|-0.858|0.858|0.514"/>
      <data pos="-324.85|84.45" frame="40" m="0.626|-0.777|0.777|0.626"/>
      <data pos="-307.3|63.2" frame="41" m="0.729|-0.682|0.682|0.729"/>
      <data pos="-289.7|41.85" frame="42" m="0.817|-0.574|0.574|0.817"/>
      <data pos="-272.15|20.6" frame="43" m="0.889|-0.455|0.455|0.889"/>
      <data pos="-254.6|-0.6" frame="44" m="0.945|-0.328|0.328|0.945"/>
      <data pos="-256.6|2.3" frame="45" m="0.948|-0.314|0.314|0.948"/>
      <data pos="-258.6|5.2" frame="46" m="0.952|-0.301|0.301|0.952"/>
      <data pos="-260.6|8.15" frame="47" m="0.956|-0.289|0.289|0.956"/>
      <data pos="-262.55|11" frame="48" m="0.960|-0.276|0.276|0.960"/>
      <data pos="-264.5|14" frame="49" m="0.964|-0.264|0.264|0.964"/>
      <data pos="-266.45|16.9" frame="50" m="0.967|-0.254|0.254|0.967"/>
      <data pos="-266.45|16.9" frame="51" m="0.967|-0.254|0.254|0.967"/>
      <data pos="-266.45|16.9" frame="52" m="0.967|-0.254|0.254|0.967"/>
      <data pos="-266.45|16.9" frame="53" m="0.967|-0.254|0.254|0.967"/>
      <data pos="-266.45|16.9" frame="54" m="0.967|-0.254|0.254|0.967"/>
      <data pos="-266.45|16.9" frame="55" m="0.967|-0.254|0.254|0.967"/>
      <data pos="-266.45|16.9" frame="56" m="0.967|-0.254|0.254|0.967"/>
      <data pos="-266.45|16.9" frame="57" m="0.967|-0.254|0.254|0.967"/>
      <data pos="-266.45|16.9" frame="58" m="0.967|-0.254|0.254|0.967"/>
      <data pos="-266.45|16.9" frame="59" m="0.967|-0.254|0.254|0.967"/>
      <data pos="-266.45|16.9" frame="60" m="0.967|-0.254|0.254|0.967"/>
      <data pos="-266.45|16.9" frame="61" m="0.967|-0.254|0.254|0.967"/>
      <data pos="-266.45|16.9" frame="62" m="0.967|-0.254|0.254|0.967"/>
      <data pos="-266.45|16.9" frame="63" m="0.967|-0.254|0.254|0.967"/>
      <data pos="-266.45|16.9" frame="64" m="0.967|-0.254|0.254|0.967"/>
      <data pos="-266.45|16.9" frame="65" m="0.967|-0.254|0.254|0.967"/>
      <data pos="-266.45|16.9" frame="66" m="0.967|-0.254|0.254|0.967"/>
      <data pos="-266.45|16.9" frame="67" m="0.967|-0.254|0.254|0.967"/>
      <data pos="-266.45|16.9" frame="68" m="0.967|-0.254|0.254|0.967"/>
      <data pos="-266.45|16.9" frame="69" m="0.967|-0.254|0.254|0.967"/>
      <data pos="-266.45|16.9" frame="70" m="0.967|-0.254|0.254|0.967"/>
      <data pos="-266.45|16.9" frame="71" m="0.967|-0.254|0.254|0.967"/>
      <data pos="-266.45|16.9" frame="72" m="0.967|-0.254|0.254|0.967"/>
      <data pos="-266.45|16.9" frame="73" m="0.967|-0.254|0.254|0.967"/>
      <data pos="-266.45|16.9" frame="74" m="0.967|-0.254|0.254|0.967"/>
      <data pos="-266.45|16.9" frame="75" m="0.967|-0.254|0.254|0.967"/>
      <data pos="-266.45|16.9" frame="76" m="0.967|-0.254|0.254|0.967"/>
      <data pos="-266.45|16.9" frame="77" m="0.967|-0.254|0.254|0.967"/>
      <data pos="-266.45|16.9" frame="78" m="0.967|-0.254|0.254|0.967"/>
      <data pos="-266.45|16.9" frame="79" m="0.967|-0.254|0.254|0.967"/>
      <data pos="-266.45|16.9" frame="80" m="0.967|-0.254|0.254|0.967"/>
      <data pos="-266.45|16.9" frame="81" m="0.967|-0.254|0.254|0.967"/>
      <data pos="-266.45|16.9" frame="82" m="0.967|-0.254|0.254|0.967"/>
      <data pos="-266.45|16.9" frame="83" m="0.967|-0.254|0.254|0.967"/>
      <data pos="-266.45|16.9" frame="84" m="0.967|-0.254|0.254|0.967"/>
      <data pos="-266.45|16.9" frame="85" m="0.967|-0.254|0.254|0.967"/>
      <data pos="-266.45|16.9" frame="86" m="0.967|-0.254|0.254|0.967"/>
      <data pos="-266.45|16.9" frame="87" m="0.967|-0.254|0.254|0.967"/>
      <data pos="-266.45|16.9" frame="88" m="0.967|-0.254|0.254|0.967"/>
    </LARGE_Arm_Top_Lower_01>
    <LARGE_Arm_Top_Lower_06>
      <data pos="-278|40.4" frame="1" m="0.001|0|0|0.001" v="0"/>
      <data pos="-403.4|158.45" frame="5" m="-0.040|-0.999|0.999|-0.040"/>
      <data pos="-423.05|174.35" frame="6" m="-0.140|-0.990|0.990|-0.140"/>
      <data pos="-428.6|184.7" frame="7" m="-0.239|-0.970|0.970|-0.239"/>
      <data pos="-434.15|190.3" frame="8" m="-0.340|-0.940|0.940|-0.340"/>
      <data pos="-434.15|190.3" frame="9" m="-0.340|-0.940|0.940|-0.340"/>
      <data pos="-434.15|190.3" frame="10" m="-0.340|-0.940|0.940|-0.340"/>
      <data pos="-278|40.4" frame="11" m="0.596|-0.801|0.801|0.596"/>
      <data pos="-278|40.4" frame="12" m="0.001|0|0|0.001" v="0"/>
    </LARGE_Arm_Top_Lower_06>
    <LARGE_Arm_Top_Lower_07>
      <data pos="-434.15|190.3" frame="1" m="0.001|0|0|0.001" v="0"/>
      <data pos="131.7|-52.55" frame="12" m="0.848|0.530|-0.530|0.848"/>
      <data pos="149.35|-50.15" frame="13" m="0.851|0.523|-0.523|0.851"/>
      <data pos="165.85|-48" frame="14" m="0.855|0.515|-0.515|0.855"/>
      <data pos="181.25|-45.95" frame="15" m="0.860|0.508|-0.508|0.860"/>
      <data pos="195.5|-44.05" frame="16" m="0.864|0.501|-0.501|0.864"/>
      <data pos="208.6|-42.25" frame="17" m="0.866|0.496|-0.496|0.866"/>
      <data pos="220.55|-40.75" frame="18" m="0.870|0.489|-0.489|0.870"/>
      <data pos="231.4|-39.3" frame="19" m="0.873|0.485|-0.485|0.873"/>
      <data pos="241.05|-38" frame="20" m="0.875|0.481|-0.481|0.875"/>
      <data pos="249.6|-36.85" frame="21" m="0.877|0.477|-0.477|0.877"/>
      <data pos="257.05|-35.9" frame="22" m="0.879|0.474|-0.474|0.879"/>
      <data pos="263.25|-35.05" frame="23" m="0.881|0.470|-0.470|0.881"/>
      <data pos="268.4|-34.4" frame="24" m="0.881|0.470|-0.470|0.881"/>
      <data pos="272.35|-33.85" frame="25" m="0.883|0.466|-0.466|0.883"/>
      <data pos="275.25|-33.5" frame="26" m="0.883|0.466|-0.466|0.883"/>
      <data pos="276.95|-33.25" frame="27" m="0.883|0.466|-0.466|0.883"/>
      <data pos="277.5|-33.15" frame="28" m="0.885|0.466|-0.466|0.885"/>
      <data pos="277.5|-33.15" frame="29" m="0.885|0.466|-0.466|0.885"/>
      <data pos="147.2|-64.05" frame="30" m="0.982|0.179|-0.179|0.982"/>
      <data pos="17|-70.15" frame="31" m="0.991|-0.118|0.118|0.991"/>
      <data pos="-119.3|-32.8" frame="32" m="0.909|-0.410|0.410|0.909"/>
      <data pos="-243.3|19.9" frame="33" m="0.746|-0.663|0.663|0.746"/>
      <data pos="-218.4|78" frame="34" m="0.001|0|0|0.001" v="0"/>
    </LARGE_Arm_Top_Lower_07>
  </act>
</root>